Workbook

Sheet Audit_Info
A1: This checklist is used for the audit checklist upload for the GLOBALG.A.P. database.
A2: (*) Mandatory entry | B2: Use multiple lines for "Key persons", "Auditors" and "Sites/PHUs".
A3: AuditID: | E3: IFA v6 Smart Aquaculture
A4: GGN*: | E4: Audited Company*:
A5: Reporting Option | B5: Please select
A6: Contact Person Name* | B6: Contact Person Surname* | C6: Email* | D6: Key persons present during the Audit, Name* | E6: Company* | F6: Position* | G6: Location of main site seen during the audit | H6: Company Profile (briefly describe company audited) | I6: Audit Date start* | J6: Audit Date end* | K6: General Notes on the audit | L6: Internal Notes on the audit | M6: Travel required between sites/PHUs (Y/N)?* | N6: Travel mode used | O6: Time (minutes) | P6: Travel Date | Q6: GAIN | R6: Auditor Name | S6: Sites audited | T6: Site audited Start Date/Time | U6: Site audited End Date/Time

Sheet Audit scope_Info
A1: Instructions
A2: The product registration in the GLOBALG.A.P. database is leading.
A5: Audit Details: IFA v6 Smart | B5: Audit type* -Initial certification audit -Audit for sites and members -Surveillance audit for sites and members -Subsequent audit -Recertification audit -Follow-up on-site audit -Modification audit | C5: Where is the audit conducted?* -On-site -On-Site + Off-Site -Off-site/Admin -Remote | D5: How is the audit conducted?* -Announced -Unannounced <48h -Unannounced 0 h -Randomly selected in case of option 2 members or site of an option 1 with QMS (GFS only) | E5: Does the audit take place in combination with any other standard or add-on? If so, indicate which standard or add-on.
B7: Sites Audited | C7: Site Type -SITE -PHU -EXTERNAL_PHU (Subcontracted) | D7: Site Name | E7: Site Address | F7: Site Coordinates
B9: GFSI recognized (post-farm) certification at the time of the inspection? * -Yes -No
B11: HACCP recognized (post-farm) certification at the time of the inspection? * -Yes -No
B13: Products | C13: Additional Data or Variety (optional) | D13: Broodstock additionally purchased? | E13: Seedlings (ova) additionally purchased? -Yes -No | F13: Seedlings (juvenile) additionally purchased? -Yes -No | G13: Feed supplied (internally or externally)? -Yes -No | H13: PO, Production of certified and non-certified products - Yes - No | I13: PO, Ownership/Purchase of certified and non-certified products - Yes - No | J13: Trade. Does the producer buy certified product from external sources - Yes - No | K13: No use of antimicrobials for the last certification cycle? -Yes -No | L13: Production system used for on-growing stage? - On/Off Bottom Cultures - Ponds and Tanks -Recirculating AQ Systems (RAS) -Net Pens -N/A (hatcheries) Other | M13: Countries of destination: one or multiple countries | N13: BroodstockInHouse | O13: Seedlings (ova) in-house, estimated organisms in no. | P13: Seedlings (juvenile) in-house, estimated organisms in no. | Q13: Farmed aquatic species, annual quantity in metric tonnes at point of harvest
B15: Products For PHUs | C15: Post harvest activity? -Yes -No | D15: PO, Production of certified and non-certified products - Yes - No | E15: PO, Ownership/Purchase of certified and non-certified products - Yes - No | F15: Trade. Does the producer buy certified product from external sources - Yes - No
B17: Products For external PHUs (Subcontracted) | C17: Post harvest activity? -Yes -No | D17: PO, Production of certified and non-certified products - Yes - No | E17: PO, Ownership/Purchase of certified and non-certified products - Yes - No | F17: Trade. Does the producer buy certified product from external sources - Yes - No
A20: Products and activities observed during the audit* | B20: Has product handling been observed during the audit? - Yes - No | C20: If yes, of which products? | D20: List all products presented during the audit: | E20: Does the producer buy products from certified production processes from external sources? | F20: If yes, which products? | G20: Has the harvest of the products been seen during this CB audit? | H20: If yes, list products

Sheet CL - IFA v6 Smart - AQ
A1: Disclaimer: Translation of normative documents: in case of doubt, the English version applies
A2: Instructions
B3: The correct values for the "Answers" column are: Text (Yes, No, N/A respectively)
B4: The "Justification" column is free text.
B5: The color of the cell reminds that this P&C cannot be answered with "Not Applicable".
B6: In case of principles and criteria are "N/A" all questions shall be put "N/A" and the relevant principles and criteria that can not be selected as "N/A" shall be put on "Yes"
B7: The "Due date" column is mandatory for the P&Cs with answer No and Major Must or Minor Must level.
A9: Standard | B9: Version | C9: Product Category | D9: Principle | E9: Section | F9: Description | G9: Criteria | H9: NIG | I9: Level | J9: Yes | K9: No | L9: N/A | M9: Answer Confirmation | N9: Method | O9: Inspection method | P9: Justification guide | Q9: Justification | R9: Due date | S9: Site 1 | T9: Site 2 | U9: Site 3 | V9: Site 4 | W9: Site 5 | X9: Site 6 | Y9: Site 7 | Z9: Site 8 | AA9: Site 9 | AB9: Site 10
A10: IFA | B10: IFA v6 Smart | C10: AQ | D10: AQ-Smart 01.01.01 | E10: AQ 01 SITE HISTORY AND SITE MANAGEMENT | F10: The producer has a reference system for identifying sites used in production, other areas, and facilities. | G10: Compliance shall require visual identification in the form of: a physical sign and a farm map which also identifies the location of water sources, storage/handling facilities, production units, entry and exit points, etc., and that can be cross-referenced to the identification system. No “N/A.” | I10: Major Must | M10: =IF(AND(J10<>"",ISBLANK(K10),ISBLANK(L10)),"Yes",IF(AND(K10<>"",ISBLANK(J10),ISBLANK(L10)),"No",IF(AND(L10<>"",ISBLANK(J10),ISBLANK(K10)),"N/A","not answered/error"))) -> not answered/error | Q10: Confirmation that a map is available and that it clearly identifies all sites. If physical signs are in place, this shall be recorded.
A11: IFA | B11: IFA v6 Smart | C11: AQ | D11: AQ-Smart 01.01.02 | E11: AQ 01 SITE HISTORY AND SITE MANAGEMENT | F11: A recording system is established for each production unit to provide a record of the production activities undertaken. | G11: Current records shall provide a history of GLOBALG.A.P. certified production at all production units. This shall be done either digitally or on paper. No “N/A.” | I11: Major Must | M11: =IF(AND(J11<>"",ISBLANK(K11),ISBLANK(L11)),"Yes",IF(AND(K11<>"",ISBLANK(J11),ISBLANK(L11)),"No",IF(AND(L11<>"",ISBLANK(J11),ISBLANK(K11)),"N/A","not answered/error"))) -> not answered/error | Q11: Identification of the site and the period where all history of activities were revised.
A12: IFA | B12: IFA v6 Smart | C12: AQ | D12: AQ-Smart 01.02.01 | E12: AQ 01 SITE HISTORY AND SITE MANAGEMENT | F12: A risk assessment is available for all sites registered for certification to evaluate whether the sites are suitable for continuing farming operations. | G12: A documented risk assessment to determine whether the sites (including rented land, structures, and equipment) are appropriate for production shall be available for all sites, considering aspects of food safety, the environment, and the health and welfare of farmed aquatic species. It shall be ready for the initial certification body (CB) audit and maintained, updated, and reviewed whenever new sites enter into production, when risks for existing ones have changed, or at least annually, whichever occurs first. The risk assessment may be based on a generic one but shall be customized to the farm situation. A list of all activities potentially affecting the aquaculture farm shall be available with regard to: potential physical, chemical (including allergens), and biological hazards. Cross-reference with AQ 20.02.16 and AQ 20.02.18. | I12: Major Must | M12: =IF(AND(J12<>"",ISBLANK(K12),ISBLANK(L12)),"Yes",IF(AND(K12<>"",ISBLANK(J12),ISBLANK(L12)),"No",IF(AND(L12<>"",ISBLANK(J12),ISBLANK(K12)),"N/A","not answered/error"))) -> not answered/error | Q12: A documented risk assessment is available with a list A list of all activities potentially affecting the aquaculture farm: potential physical, chemical (including allergens), and biological hazards. Document identification name: code: revision: date:
A13: IFA | B13: IFA v6 Smart | C13: AQ | D13: AQ-Smart 01.02.02 | E13: AQ 01 SITE HISTORY AND SITE MANAGEMENT | F13: A management plan that establishes strategies for minimizing the risks identified in the risk assessment for operation suitability has been developed and implemented and is reviewed regularly. | G13: A management plan shall address the risks identified in AQ 01.02.01 and describe the hazard control procedures that justify that the site in question is suitable for production, ensuring sustainability and effectiveness. This plan shall be appropriate to farm operations, and there shall be evidence of its implementation. The plan shall address maintenance of grounds and areas within the site to prevent contamination. The plan shall be reviewed annually, or whenever changes occur that may impact the safety of food production and impact the food safety plan, whichever occurs first. | I13: Major Must | M13: =IF(AND(J13<>"",ISBLANK(K13),ISBLANK(L13)),"Yes",IF(AND(K13<>"",ISBLANK(J13),ISBLANK(L13)),"No",IF(AND(L13<>"",ISBLANK(J13),ISBLANK(K13)),"N/A","not answered/error"))) -> not answered/error | Q13: A management pla address the risks identified in AQ 01.02.01. Document identification name: code: revision: date:
A14: IFA | B14: IFA v6 Smart | C14: AQ | D14: AQ-Smart 01.02.03 | E14: AQ 01 SITE HISTORY AND SITE MANAGEMENT | F14: All structures are located, designed, and constructed to facilitate proper cleaning and pest control. | G14: Where appropriate, the design and layout shall permit compliance with good hygiene practices, including protection against cross contamination between and during operations. This requirement shall include all adjoining rooms, equipment, facilities, and feeding systems. A program of self-assessments/internal audits shall be established, implemented, and maintained to ensure the sites and equipment are routinely maintained in a suitable condition to ensure food safety, as applicable to the activity of the site. Self-assessments/Internal audits can be at an interval determined by the producer in accordance with the assessed risk. | I14: Major Must | M14: =IF(AND(J14<>"",ISBLANK(K14),ISBLANK(L14)),"Yes",IF(AND(K14<>"",ISBLANK(J14),ISBLANK(L14)),"No",IF(AND(L14<>"",ISBLANK(J14),ISBLANK(K14)),"N/A","not answered/error"))) -> not answered/error
A15: IFA | B15: IFA v6 Smart | C15: AQ | D15: AQ-Smart 01.03.01 | E15: AQ 01 SITE HISTORY AND SITE MANAGEMENT | F15: Farm management is able to demonstrate awareness at interview of compliance with legislation. | G15: In the interview, farm management shall be able to demonstrate how it fulfills its legal obligations with respect to the food safety, farmed aquatic species health and welfare, feed formulation, environment, biodiversity, and workers’ health and safety legislation applicable to its enterprise. No “N/A.” | I15: Major Must | M15: =IF(AND(J15<>"",ISBLANK(K15),ISBLANK(L15)),"Yes",IF(AND(K15<>"",ISBLANK(J15),ISBLANK(L15)),"No",IF(AND(L15<>"",ISBLANK(J15),ISBLANK(K15)),"N/A","not answered/error"))) -> not answered/error
A16: IFA | B16: IFA v6 Smart | C16: AQ | D16: AQ-Smart 01.03.02 | E16: AQ 01 SITE HISTORY AND SITE MANAGEMENT | F16: Aquaculture farms are registered as such with the relevant competent authority as required by national legislation for the specific farmed aquatic species. | G16: Registration and license documents shall be available. Examples include: seabed leases and consents for discharge of effluent and licenses/concessions from authority to grow a set biomass of aquaculture products or allocation of feed quota. No “N/A.” | I16: Major Must | M16: =IF(AND(J16<>"",ISBLANK(K16),ISBLANK(L16)),"Yes",IF(AND(K16<>"",ISBLANK(J16),ISBLANK(L16)),"No",IF(AND(L16<>"",ISBLANK(J16),ISBLANK(K16)),"N/A","not answered/error"))) -> not answered/error | Q16: Document identification name/type of licence: code: revision: date: institution that issue the license: Date of validity of the license/permit.
A17: IFA | B17: IFA v6 Smart | C17: AQ | D17: AQ-Smart 02.01 | E17: AQ 02 INTERNAL DOCUMENTATION | F17: In the initial phase (initial certification body (CB) audit) of application of the standard, site records demonstrate compliance with the standard for the last three months. | G17: Records shall be in place for the last three months demonstrating compliance sufficient to achieve GLOBALG.A.P. certification. No “N/A.” | I17: Major Must | M17: =IF(AND(J17<>"",ISBLANK(K17),ISBLANK(L17)),"Yes",IF(AND(K17<>"",ISBLANK(J17),ISBLANK(L17)),"No",IF(AND(L17<>"",ISBLANK(J17),ISBLANK(K17)),"N/A","not answered/error"))) -> not answered/error | Q17: all records verified show as a minimum three months of recording. Example: XXXXXXXXXXX For consecutive audits, report: "Consecutive audit."
A18: IFA | B18: IFA v6 Smart | C18: AQ | D18: AQ-Smart 02.02 | E18: AQ 02 INTERNAL DOCUMENTATION | F18: A documented system with procedures and work instructions covering all processes is available and implemented. | G18: Documented procedures and work instructions shall be available on the site demonstrating compliance with food safety, legal, and standard requirements, including supplier approval procedures. No “N/A.” | I18: Major Must | M18: =IF(AND(J18<>"",ISBLANK(K18),ISBLANK(L18)),"Yes",IF(AND(K18<>"",ISBLANK(J18),ISBLANK(L18)),"No",IF(AND(L18<>"",ISBLANK(J18),ISBLANK(K18)),"N/A","not answered/error"))) -> not answered/error | Q18: Document identification name: code: revision: date:
A19: IFA | B19: IFA v6 Smart | C19: AQ | D19: AQ-Smart 02.03 | E19: AQ 02 INTERNAL DOCUMENTATION | F19: The aquaculture farm and the production units have an organizational structure with defined responsibilities. | G19: A clear organizational structure identifying the job functions and responsibilities shall be established, implemented, and maintained. Workers whose activities have a potential impact on food safety shall be identified. No “N/A.” | I19: Major Must | M19: =IF(AND(J19<>"",ISBLANK(K19),ISBLANK(L19)),"Yes",IF(AND(K19<>"",ISBLANK(J19),ISBLANK(L19)),"No",IF(AND(L19<>"",ISBLANK(J19),ISBLANK(K19)),"N/A","not answered/error"))) -> not answered/error | Q19: Document identification name: code: revision: date:
A20: IFA | B20: IFA v6 Smart | C20: AQ | D20: AQ-Smart 02.04 | E20: AQ 02 INTERNAL DOCUMENTATION | F20: Geographical coordinates identify all operations of the farm. | G20: Geographical coordinates shall identify all sites where the actual aquatic operation takes place. The coordinates shall refer to the center of the production site (smaller sites; <1 ha) or the corners of the contours of the production sites (larger sites; >1 ha). The coordinates (degrees and minutes of latitude and longitude) shall be within an accuracy of two decimals in the geographical minutes (e.g., 15º22.65′ N; 22º43.78′ E) using the WGS-84 coordinate system. No “N/A.” | I20: Major Must | M20: =IF(AND(J20<>"",ISBLANK(K20),ISBLANK(L20)),"Yes",IF(AND(K20<>"",ISBLANK(J20),ISBLANK(L20)),"No",IF(AND(L20<>"",ISBLANK(J20),ISBLANK(K20)),"N/A","not answered/error"))) -> not answered/error | Q20: Geographical coordinates of all sites:
A21: IFA | B21: IFA v6 Smart | C21: AQ | D21: AQ-Smart 02.05 | E21: AQ 02 INTERNAL DOCUMENTATION | F21: Records for auditing purposes are up-to-date. Records are kept for a minimum period of two years, unless a longer period is required. | G21: The producer shall keep up-to-date records, including those relating to food safety, for a minimum of two years, or a longer period depending on customer or legal requirements. If the shelf life of the product exceeds two years, records shall be retained for a period that exceeds the shelf life. Electronic records shall be valid and if they are used, the producer shall be responsible for maintaining back-ups of the information. Documents shall be securely stored, effectively controlled, and readily accessible. For the initial certification body (CB) audit, the producer shall keep records from at least three months prior to the date of the CB audit or from the day of registration, whichever is longer. New applicants shall have full records for each area covered by the registration with all of the activities related to GLOBALG.A.P. documentation required for this area. These records shall be available for the current cycle before the initial CB audit. No “N/A.” | I21: Major Must | M21: =IF(AND(J21<>"",ISBLANK(K21),ISBLANK(L21)),"Yes",IF(AND(K21<>"",ISBLANK(J21),ISBLANK(L21)),"No",IF(AND(L21<>"",ISBLANK(J21),ISBLANK(K21)),"N/A","not answered/error"))) -> not answered/error | Q21: examples of records verified: -XXXXXXX -XXXXXXX -XXXXXXX Describe where the records are kept/stored.
A22: IFA | B22: IFA v6 Smart | C22: AQ | D22: AQ-Smart 02.06 | E22: AQ 02 INTERNAL DOCUMENTATION | F22: A procedure is in place to manage and control documents and records. | G22: A procedure describing the management of documented information shall be implemented and maintained. A method of tracking document changes shall be established to ensure workers are accessing the most recent version. | I22: Major Must | M22: =IF(AND(J22<>"",ISBLANK(K22),ISBLANK(L22)),"Yes",IF(AND(K22<>"",ISBLANK(J22),ISBLANK(L22)),"No",IF(AND(L22<>"",ISBLANK(J22),ISBLANK(K22)),"N/A","not answered/error"))) -> not answered/error | Q22: Document identification name: code: revision: date:
A23: IFA | B23: IFA v6 Smart | C23: AQ | D23: AQ-Smart 02.07 | E23: AQ 02 INTERNAL DOCUMENTATION | F23: The producer completes a minimum of one self-assessment/internal audit annually to the standard. | G23: There shall be documented evidence that, in Option 1 individual producers, a self-assessment has been completed under the responsibility of the producer (this may be carried out by a person different from the producer). Self-assessments shall include all applicable principles and criteria, even when a subcontracted company carries them out. A documented self-assessment for individual producers shall contain comments regarding the evidence observed for all not applicable and non-compliant Major Must and Minor Must principles and criteria. For internal farm and quality management system (QMS) audits, comments shall follow “GLOBALG.A.P. general regulations – Rules for producer groups and multisite producers with QMS.” The self-assessment shall be completed before the certification body (CB) audit (see “GLOBALG.A.P. general regulations – Rules for individual producers”). No “N/A,” except for multisite producers with QMS and producer groups, which are covered by the internal QMS audit. | I23: Major Must | M23: =IF(AND(J23<>"",ISBLANK(K23),ISBLANK(L23)),"Yes",IF(AND(K23<>"",ISBLANK(J23),ISBLANK(L23)),"No",IF(AND(L23<>"",ISBLANK(J23),ISBLANK(K23)),"N/A","not answered/error"))) -> not answered/error | Q23: Date of self-assessment or internal farm audit: XXX Initials/abbreviation of person performing the internal audit:XXX
A24: IFA | B24: IFA v6 Smart | C24: AQ | D24: AQ-Smart 02.08 | E24: AQ 02 INTERNAL DOCUMENTATION | F24: Effective corrective actions are taken to address non-conformances detected during the self-assessments/internal audits. | G24: Corrective actions shall be documented. Any necessary changes shall be implemented. Compliance with all applicable Major Musts and at least 95% of applicable Minor Musts is required. “N/A” only if no non-conformances are detected during self-assessments/internal audits. | I24: Major Must | M24: =IF(AND(J24<>"",ISBLANK(K24),ISBLANK(L24)),"Yes",IF(AND(K24<>"",ISBLANK(J24),ISBLANK(L24)),"No",IF(AND(L24<>"",ISBLANK(J24),ISBLANK(K24)),"N/A","not answered/error"))) -> not answered/error | Q24: Number of non-compliances detected: Number of non-compliances still open:
A25: IFA | B25: IFA v6 Smart | C25: AQ | D25: AQ-Smart 02.09 | E25: AQ 02 INTERNAL DOCUMENTATION | F25: A continuous improvement plan is documented. | G25: A continuous improvement plan based on self-assessments/internal audits and certification body (CB) audits shall be documented. Continuous improvements can be shown as a reduction in overall non-conformances during self-assessments/internal audits, evaluation of a root cause analysis, documented actions, or other applicable activities. | I25: Major Must | M25: =IF(AND(J25<>"",ISBLANK(K25),ISBLANK(L25)),"Yes",IF(AND(K25<>"",ISBLANK(J25),ISBLANK(L25)),"No",IF(AND(L25<>"",ISBLANK(J25),ISBLANK(K25)),"N/A","not answered/error"))) -> not answered/error | Q25: Continuous improvement plan XX Dated YYYY/MM/DD Example of self-defined target XXXXXX - DATE OF ACHIEVEMENT PREVIEWED : XXX -
A26: IFA | B26: IFA v6 Smart | C26: AQ | D26: AQ-Smart 02.10 | E26: AQ 02 INTERNAL DOCUMENTATION | F26: There is evidence that a continuous improvement plan is implemented. | G26: A continuous improvement plan based on self-assessments/internal audits and certification body (CB) audits shall be implemented. Continuous improvements can be shown as a reduction in overall non-conformances during self-assessments/internal audits, resource management plans documenting improvements, or other applicable activities. | I26: Major Must | M26: =IF(AND(J26<>"",ISBLANK(K26),ISBLANK(L26)),"Yes",IF(AND(K26<>"",ISBLANK(J26),ISBLANK(L26)),"No",IF(AND(L26<>"",ISBLANK(J26),ISBLANK(K26)),"N/A","not answered/error"))) -> not answered/error | Q26: Document identification name: code: revision: date:
A27: IFA | B27: IFA v6 Smart | C27: AQ | D27: AQ-Smart 03.01 | E27: AQ 03 HYGIENE | F27: The farm has a documented hygiene risk assessment. | G27: The documented hygiene risk assessment shall be appropriate to the activities taking place on the farm and shall be reviewed annually and updated when changes (e.g., other activities) occur. No “N/A.” | I27: Major Must | M27: =IF(AND(J27<>"",ISBLANK(K27),ISBLANK(L27)),"Yes",IF(AND(K27<>"",ISBLANK(J27),ISBLANK(L27)),"No",IF(AND(L27<>"",ISBLANK(J27),ISBLANK(K27)),"N/A","not answered/error"))) -> not answered/error | Q27: Document identification name: code: revision: date: production stages covered: All production stages covered in the hygiene risk assessment are equivalent to those covered in the certificate, either performed by the producer or subcontracted. Detail/List all different production, harvest, and postharvest processes seen.
... A41: IFA | B41: IFA v6 Smart | C41: AQ | D41: AQ-Smart 04.02.06 | E41: AQ 04 WORKERS’ WELL-BEING: OCCUPATIONAL HEALTH, SAFETY, AND WELFARE | F41: Where workers with special duties are identified and competence in their tasks shall be demonstrated, records are available. | G41: Workers handling and/or administering veterinary medicines, chemicals, disinfectants, biocides, and/or other hazardous substances and all workers operating dangerous or complex equipment as defined in the risk assessment in AQ 04.01.01 shall have evidence of competence or details of other such qualifications. Records shall identify workers who carry out such tasks and can demonstrate competence (certificate of training and/or records of training with evidence of attendance). This shall include compliance with applicable legislation. Cross-reference with AQ 04.02.01. For workers administering medicines, evidence of adequate experience shall be in place. No “N/A.” | I41: Major Must | M41: =IF(AND(J41<>"",ISBLANK(K41),ISBLANK(L41)),"Yes",IF(AND(K41<>"",ISBLANK(J41),ISBLANK(L41)),"No",IF(AND(L41<>"",ISBLANK(J41),ISBLANK(K41)),"N/A","not answered/error"))) -> not answered/error | Q41: Topic of training: XXXXX Number of Workers: XXX; Traning Date: DD/MM/YY - Initials of the name of Trainer(s): XXXXX
A42: IFA | B42: IFA v6 Smart | C42: AQ | D42: AQ-Smart 04.03.01 | E42: AQ 04 WORKERS’ WELL-BEING: OCCUPATIONAL HEALTH, SAFETY, AND WELFARE | F42: Accident and emergency procedures are displayed and communicated. | G42: Instructions based on the accident and emergency procedures shall be clearly displayed in accessible and visible location(s) for workers, visitors, and subcontractors. A named person is assigned as responsible for such procedures. These instructions shall be available in the relevant language(s) of the workforce and/or in pictograms. The procedures shall be appropriate to the size and type of production and level of risk and take into account all applicable national legal requirements. Emergency evacuation equipment and survival gear (where required) shall be accessible and of sufficient quantity and quality. The procedures shall identify the following: - The farm address, map, or other location information (e.g., GPS coordinates) - The contact person(s) - An up-to-date list of relevant telephone numbers (police, ambulance, hospital, fire brigade, access to emergency health care on site or by means of transport, and the suppliers of electricity, water, and gas) - Emergency evacuation procedures, where applicable Examples of other procedures that can be included: - The location of the nearest means of communication (telephone, radio) - How and where to contact local medical services, hospitals, and other emergency services (Questions for contact with emergency services: WHERE did it happen? WHAT happened? HOW MANY injured people? WHAT kind of injuries? WHO is calling?) - The location of fire extinguisher(s) at structures and all buildings (including worker accommodation) that are considered a potential fire risk - The locations of emergency exits - Emergency cut-offs for electricity, gas, fuel, and water lines - How to record accidents and near misses and introduce preventive action - How to deal with accidents involving chemicals following safety data sheets (SDSs) | I42: Minor Must | M42: =IF(AND(J42<>"",ISBLANK(K42),ISBLANK(L42)),"Yes",IF(AND(K42<>"",ISBLANK(J42),ISBLANK(L42)),"No",IF(AND(L42<>"",ISBLANK(J42),ISBLANK(K42)),"N/A","not answered/error"))) -> not answered/error
A43: IFA | B43: IFA v6 Smart | C43: AQ | D43: AQ-Smart 04.03.02 | E43: AQ 04 WORKERS’ WELL-BEING: OCCUPATIONAL HEALTH, SAFETY, AND WELFARE | F43: Warning signs identify all potential hazards, emergency exits, and escape routes. | G43: Permanent and legible signs shall indicate potential hazards, emergency exits, and escape routes. This shall include indicating, where applicable: ongoing treatments, waste pits, fuel tanks, workshops, warning signs in all buildings or permanent structures showing emergency exits, escape routes, safety equipment (fire extinguisher, washing facilities, etc.) and safety alarms (fire, CO2, evacuation, tornado, etc.) and access doors of the storage facilities for chemicals. Fire exits and escape routes shall be kept open, accessible, and clear of obstacles to permit safe evacuation in case of an emergency. Warning signs shall be present and in the predominant language(s) of the workforce and/or in pictograms. No “N/A.” | I43: Minor Must | M43: =IF(AND(J43<>"",ISBLANK(K43),ISBLANK(L43)),"Yes",IF(AND(K43<>"",ISBLANK(J43),ISBLANK(L43)),"No",IF(AND(L43<>"",ISBLANK(J43),ISBLANK(K43)),"N/A","not answered/error"))) -> not answered/error
A44: IFA | B44: IFA v6 Smart | C44: AQ | D44: AQ-Smart 04.03.03 | E44: AQ 04 WORKERS’ WELL-BEING: OCCUPATIONAL HEALTH, SAFETY, AND WELFARE | F44: Safety advice for substances hazardous to workers’ health and safety is immediately available and accessible. | G44: Emergency information (website, telephone number, safety data sheet, etc.) on each hazardous substance shall be available and accessible in the appropriate locations. Cross-reference with AQ 19.01.02. | I44: Minor Must | M44: =IF(AND(J44<>"",ISBLANK(K44),ISBLANK(L44)),"Yes",IF(AND(K44<>"",ISBLANK(J44),ISBLANK(L44)),"No",IF(AND(L44<>"",ISBLANK(J44),ISBLANK(K44)),"N/A","not answered/error"))) -> not answered/error
A45: IFA | B45: IFA v6 Smart | C45: AQ | D45: AQ-Smart 04.03.04 | E45: AQ 04 WORKERS’ WELL-BEING: OCCUPATIONAL HEALTH, SAFETY, AND WELFARE | F45: First aid kits are accessible at all permanent sites and fields near the work. | G45: Complete and maintained first aid kits (i.e., complete and maintained according to local recommendations and appropriate to the activities being carried out) shall be available and accessible at all permanent sites and present in selected transport means (vessel, vehicle, etc.) where required by the risk assessment in AQ 04.01.01. | I45: Minor Must | M45: =IF(AND(J45<>"",ISBLANK(K45),ISBLANK(L45)),"Yes",IF(AND(K45<>"",ISBLANK(J45),ISBLANK(L45)),"No",IF(AND(L45<>"",ISBLANK(J45),ISBLANK(K45)),"N/A","not answered/error"))) -> not answered/error | Q45: first aid kit checked located in XXXXXX
A46: IFA | B46: IFA v6 Smart | C46: AQ | D46: AQ-Smart 04.03.05 | E46: AQ 04 WORKERS’ WELL-BEING: OCCUPATIONAL HEALTH, SAFETY, AND WELFARE | F46: There is always at least one person trained in first aid present on the farm whenever on-farm activities are being carried out. | G46: There shall always be at least one person trained in first aid (with valid training certificate) present on the farm whenever on-farm activities are being carried out. | I46: Minor Must | M46: =IF(AND(J46<>"",ISBLANK(K46),ISBLANK(L46)),"Yes",IF(AND(K46<>"",ISBLANK(J46),ISBLANK(L46)),"No",IF(AND(L46<>"",ISBLANK(J46),ISBLANK(K46)),"N/A","not answered/error"))) -> not answered/error
A47: IFA | B47: IFA v6 Smart | C47: AQ | D47: AQ-Smart 04.04.01 | E47: AQ 04 WORKERS’ WELL-BEING: OCCUPATIONAL HEALTH, SAFETY, AND WELFARE | F47: Workers, visitors, and subcontractors are equipped with suitable personal protective equipment (PPE). | G47: Complete sets of suitable PPE, enabling compliance with label instructions and/or legal requirements and/or requirements as authorized by a competent authority, shall be available on the farm, utilized, and in a good state of repair. Complying with label requirements and/or requirements in the risk assessment for on-farm operations may include use of some of the following: rubber boots or other appropriate footwear, waterproof clothing, protective overalls, rubber gloves, face masks, appropriate respiratory equipment (including replacement filters), ear and eye protection devices, life-jackets, etc. There shall be evidence that the provided PPE is used by the workers. No “N/A.” | I47: Major Must | M47: =IF(AND(J47<>"",ISBLANK(K47),ISBLANK(L47)),"Yes",IF(AND(K47<>"",ISBLANK(J47),ISBLANK(L47)),"No",IF(AND(L47<>"",ISBLANK(J47),ISBLANK(K47)),"N/A","not answered/error"))) -> not answered/error | Q47: PPE are available and suitable. Example of PPE used and the activity: -XXXXX for XXXXXX -XXXXX for XXXXXXX
A48: IFA | B48: IFA v6 Smart | C48: AQ | D48: AQ-Smart 04.04.02 | E48: AQ 04 WORKERS’ WELL-BEING: OCCUPATIONAL HEALTH, SAFETY, AND WELFARE | F48: Personal protective equipment (PPE) is maintained in clean conditions and stored appropriately so as not to pose any contamination risk to personal items. | G48: PPE shall be kept clean according to the type of use and degree of potential contamination and stored in a ventilated place. Protective clothing shall be laundered separately from personal clothing. Reusable gloves shall be washed before removal. Dirty and damaged PPE and expired filter cartridges shall be disposed of appropriately. Single-use items (gloves, overalls, etc.) shall be disposed of after one use. PPE shall be stored in a manner that prevents cross contamination with chemicals. No “N/A.” | I48: Major Must | M48: =IF(AND(J48<>"",ISBLANK(K48),ISBLANK(L48)),"Yes",IF(AND(K48<>"",ISBLANK(J48),ISBLANK(L48)),"No",IF(AND(L48<>"",ISBLANK(J48),ISBLANK(K48)),"N/A","not answered/error"))) -> not answered/error
A49: IFA | B49: IFA v6 Smart | C49: AQ | D49: AQ-Smart 04.05.01 | E49: AQ 04 WORKERS’ WELL-BEING: OCCUPATIONAL HEALTH, SAFETY, AND WELFARE | F49: A member of the management is clearly identifiable as responsible for the workers’ health, safety, and welfare. | G49: Documentation shall be available that clearly identifies and names the member of management who is responsible for ensuring compliance with and implementation of existing, current, and relevant national and local regulations on workers’ health, safety, and welfare. | I49: Major Must | M49: =IF(AND(J49<>"",ISBLANK(K49),ISBLANK(L49)),"Yes",IF(AND(K49<>"",ISBLANK(J49),ISBLANK(L49)),"No",IF(AND(L49<>"",ISBLANK(J49),ISBLANK(K49)),"N/A","not answered/error"))) -> not answered/error | Q49: Position of responsible for workers' health, safety and welfare.
A50: IFA | B50: IFA v6 Smart | C50: AQ | D50: AQ-Smart 04.05.02 | E50: AQ 04 WORKERS’ WELL-BEING: OCCUPATIONAL HEALTH, SAFETY, AND WELFARE | F50: There is communication between management and workers on issues related to their health, safety, and welfare. | G50: Records shall show that communication between management and workers about health, safety, and welfare issues can take place openly (i.e., without fear of intimidation or retaliation) and at least once a year. - It shall be emphasized to workers that, with reasonable justification, they shall remove themselves from unsafe work. The use of this right in good faith shall eliminate any retaliation or consequence to the workers. - If accidents, near misses, or other dangerous incidents occur, they shall be reported and the cause determined and discussed with the workers. - Management shall define corrective actions to prevent recurrence of similar incidents and clearly explain the corrective actions to the workers. - Workers shall explain to management situations where they feel exposed to risk. - Management shall explain procedures for eliminating or reducing risk detected by workers. The certification body (CB) auditor is not required to make judgments about the content, accuracy, or outcome of such communications. There shall be evidence that the concerns of the workers about health, safety, and welfare are being addressed. | I50: Major Must | M50: =IF(AND(J50<>"",ISBLANK(K50),ISBLANK(L50)),"Yes",IF(AND(K50<>"",ISBLANK(J50),ISBLANK(L50)),"No",IF(AND(L50<>"",ISBLANK(J50),ISBLANK(K50)),"N/A","not answered/error"))) -> not answered/error | Q50: Identification of the record of the last meeting name/code: XXX date/edition: XXX
A51: IFA | B51: IFA v6 Smart | C51: AQ | D51: AQ-Smart 04.05.03 | E51: AQ 04 WORKERS’ WELL-BEING: OCCUPATIONAL HEALTH, SAFETY, AND WELFARE | F51: On-site living quarters are compliant with applicable local regulations, habitable, and equipped with basic services and facilities. | G51: The on-site living quarters for the workers shall be habitable and have a sound roof, windows, and doors, as well as the basic services of potable water, hygienic toilets, cooking facilities, and drains. At a minimum, the quarters shall comply with the local health and safety regulations. Living quarters shall be away from any chemical hazards (including fire hazards, inflammable substances or hazards, etc.), biological hazards (mold, sewage, etc.), and physical hazards (noise, radiation, poor ventilation, extreme temperatures, etc.) identified in the risk assessment. If there are no drains, septic pits may be acceptable if compliant with local regulations. | I51: Major Must | M51: =IF(AND(J51<>"",ISBLANK(K51),ISBLANK(L51)),"Yes",IF(AND(K51<>"",ISBLANK(J51),ISBLANK(L51)),"No",IF(AND(L51<>"",ISBLANK(J51),ISBLANK(K51)),"N/A","not answered/error"))) -> not answered/error | Q51: If applicable, list the number of workers/families living on the farm.
A52: IFA | B52: IFA v6 Smart | C52: AQ | D52: AQ-Smart 04.05.04 | E52: AQ 04 WORKERS’ WELL-BEING: OCCUPATIONAL HEALTH, SAFETY, AND WELFARE | F52: Transportation provided to workers is safe. | G52: Transportation shall be safe for workers and take into account applicable safety requirements and regulations. | I52: Minor Must | M52: =IF(AND(J52<>"",ISBLANK(K52),ISBLANK(L52)),"Yes",IF(AND(K52<>"",ISBLANK(J52),ISBLANK(L52)),"No",IF(AND(L52<>"",ISBLANK(J52),ISBLANK(K52)),"N/A","not answered/error"))) -> not answered/error
A53: IFA | B53: IFA v6 Smart | C53: AQ | D53: AQ-Smart 04.05.05 | E53: AQ 04 WORKERS’ WELL-BEING: OCCUPATIONAL HEALTH, SAFETY, AND WELFARE | F53: The producer is compliant with the GRASP v2 add-on (assessed by the same certification body (CB) conducting the audit for the Integrated Farm Assurance (IFA) standard for aquaculture). | G53: The producer shall be compliant with the GRASP v2 add-on, covering all stages of production included under the certification: hatchery, grow-out, and any post-harvest handling done by the same legal entity as the farm. Regarding subcontractors, refer to the GRASP v2 general rules. A compliant GRASP v2 result shall be required in order to be in compliance with AQ 04.05.05 and to receive GLOBALG.A.P. certification for the IFA standard for aquaculture. This applies for all farmed aquatic species, regardless of whether destined to be labeled or only having valid GLOBALG.A.P. certification. No “N/A.” | I53: Major Must | M53: =IF(AND(J53<>"",ISBLANK(K53),ISBLANK(L53)),"Yes",IF(AND(K53<>"",ISBLANK(J53),ISBLANK(L53)),"No",IF(AND(L53<>"",ISBLANK(J53),ISBLANK(K53)),"N/A","not answered/error"))) -> not answered/error | Q53: Date(s) of GRASP assessment: Date of Letter of conformance:
A54: IFA | B54: IFA v6 Smart | C54: AQ | D54: AQ-Smart 05.01 | E54: AQ 05 OUTSOURCED ACTIVITIES (SUBCONTRACTORS) | F54: The producer ensures that outsourced activities comply with the principles and criteria of the standard which are relevant to the services provided. | G54: The producer shall verify that tasks performed by subcontractors are compliant with the relevant principles and criteria of this standard. This verification shall be recorded and made available during the certification body (CB) audit. Based on the subcontractor services: i) GLOBALG.A.P. approved CB is allowed to verify compliance through a physical assessment, or ii) A GLOBALG.A.P. approved CB may assess the subcontractor directly. The subcontractor shall receive a letter of conformance from the CB with the following information: 1) Date of CB assessment 2) Name of the CB 3) Auditor name 4) Details of the subcontractor 5) List of the assessed principles and criteria Other certificates issued to subcontractors against standards that are not officially recognized by GLOBALG.A.P. are not valid evidence of compliance with GLOBALG.A.P. All subcontractors physically handling live farmed aquatic species shall have evidence of animal welfare training. Any activity performed by subcontractors shall follow legislation, including when outside the farm (subcontracted companies removing waste, sludge, old equipment, etc.). | I54: Major Must | M54: =IF(AND(J54<>"",ISBLANK(K54),ISBLANK(L54)),"Yes",IF(AND(K54<>"",ISBLANK(J54),ISBLANK(L54)),"No",IF(AND(L54<>"",ISBLANK(J54),ISBLANK(K54)),"N/A","not answered/error"))) -> not answered/error | Q54: Examples of subcontracted activities checked: Specific standard criteria related to the subcontracted: Identify which of the three situations applies (1, 2 or 3):
A55: IFA | B55: IFA v6 Smart | C55: AQ | D55: AQ-Smart 06.01.01 | E55: AQ 06 ENVIRONMENTAL AND BIODIVERSITY MANAGEMENT | F55: Waste products and sources of pollution are identified and classified in all areas of the farm. | G55: Possible waste products (paper, cardboard, plastic, oil, etc.) and pollution (exhaust smoke, oil, fuel, noise, effluent, chemicals, feed waste, algae produced during net cleaning, etc.) produced by the farm processes have been listed. Waste products shall be identified and classified by: - type - methods of storage - disposal - recycling - reuse Documented evidence shall be available. | I55: Major Must | M55: =IF(AND(J55<>"",ISBLANK(K55),ISBLANK(L55)),"Yes",IF(AND(K55<>"",ISBLANK(J55),ISBLANK(L55)),"No",IF(AND(L55<>"",ISBLANK(J55),ISBLANK(K55)),"N/A","not answered/error"))) -> not answered/error | Q55: Document identification name: code: revision: date:
A56: IFA | B56: IFA v6 Smart | C56: AQ | D56: AQ-Smart 06.02.01 | E56: AQ 06 ENVIRONMENTAL AND BIODIVERSITY MANAGEMENT | F56: A comprehensive, current, and documented waste management system is implemented. | G56: A comprehensive, current, and documented waste management system that covers waste reduction, pollution, and waste recycling shall be available. Air, soil, and water contamination shall be considered where relevant, along with all products and sources identified (organic and inorganic). The waste management system shall include the list of the products and for each of them, the intended reuse/recycle/disposal methods, and where relevant the frequency of collection and removal. The waste management system shall be part of the environmental management plan (EMP). | I56: Major Must | M56: =IF(AND(J56<>"",ISBLANK(K56),ISBLANK(L56)),"Yes",IF(AND(K56<>"",ISBLANK(J56),ISBLANK(L56)),"No",IF(AND(L56<>"",ISBLANK(J56),ISBLANK(K56)),"N/A","not answered/error"))) -> not answered/error | Q56: Document identification name: code: revision: date:
A57: IFA | B57: IFA v6 Smart | C57: AQ | D57: AQ-Smart 06.02.02 | E57: AQ 06 ENVIRONMENTAL AND BIODIVERSITY MANAGEMENT | F57: The site is kept in a tidy and orderly condition. | G57: Visual assessment shall show that waste and litter are stored in the designated locations (tanks, bins, others). Incidental waste is acceptable as well as waste from the current day’s work. | I57: Major Must | M57: =IF(AND(J57<>"",ISBLANK(K57),ISBLANK(L57)),"Yes",IF(AND(K57<>"",ISBLANK(J57),ISBLANK(L57)),"No",IF(AND(L57<>"",ISBLANK(J57),ISBLANK(K57)),"N/A","not answered/error"))) -> not answered/error
A58: IFA | B58: IFA v6 Smart | C58: AQ | D58: AQ-Smart 06.02.03 | E58: AQ 06 ENVIRONMENTAL AND BIODIVERSITY MANAGEMENT | F58: Holding areas for diesel and other fuel oil tanks are environmentally safe. | G58: Holding areas shall be maintained in manner that mitigates risks to the environment. The minimum requirement is a bunded area, which shall be impervious and be able to contain at least 150% of the largest tank stored within it. There shall be no-smoking signs displayed and appropriate fire emergency provisions made nearby. | I58: Minor Must | M58: =IF(AND(J58<>"",ISBLANK(K58),ISBLANK(L58)),"Yes",IF(AND(K58<>"",ISBLANK(J58),ISBLANK(L58)),"No",IF(AND(L58<>"",ISBLANK(J58),ISBLANK(K58)),"N/A","not answered/error"))) -> not answered/error
A59: IFA | B59: IFA v6 Smart | C59: AQ | D59: AQ-Smart 06.03.01 | E59: AQ 06 ENVIRONMENTAL AND BIODIVERSITY MANAGEMENT | F59: An environmental impact assessment (EIA) and an environmental risk assessment (ERA), both including biodiversity, are in place. | G59: An EIA and an ERA, both including biodiversity, shall be reviewed and shall be updated following relevant changes in the farm operations with respect to environmental threats. Legal compliance on all issues shall be demonstrated. Please refer to guideline AQ I, "Examples of environmental impact assessment (EIA), environmental risk assessment (ERA), and respective environmental management plans (EMPs)" and to guideline AQ II, “Biodiversity in environmental impact assessment” and guideline AQ III, “Environmental parameters of relevance based on the aquaculture system used.” Qualified persons who can show documented evidence of their competence shall prepare the ERA. Minimum requirements for an EIA shall include the evaluation of the following. If there is no monitoring of some of these parameters, the farm shall properly justify why is not applicable. Effluent - Effluent dissolved oxygen (DO) - Effluent ratio BOD5/COD (biochemical oxygen demand/chemical oxygen demand) - Effluent Kjeldahl nitrogen, nitrate, and nitrite load - Effluent phosphorus load: feed and fertilizers - Effluent suspended solids load - Salinity - pH Other waste - Disposal of solid wastes and litter - Use and legal disposal of all chemical compounds (refer to AQ 19.02), including pharmaceuticals - Emission of light, sound, and vibrations - Emission of exhaust gases Requirements for an ERA may be, but are not restricted to, the following processes that do not normally occur, but may happen accidentally during the course of operations: - Accidental spill during storage and handling of chemical compounds and fuels - Emissions resulting from fire and fire extinguishing - Escapes of farmed aquatic species, including seedlings (eggs, larvae, others) and their parasites - Release of pathogens and/or disinfectants - Salinization of groundwater and freshwater bodies - Temporary exceeding of water discharge limits - Disposal of water used for washing and cleaning purposes No “N/A.” | I59: Major Must | M59: =IF(AND(J59<>"",ISBLANK(K59),ISBLANK(L59)),"Yes",IF(AND(K59<>"",ISBLANK(J59),ISBLANK(L59)),"No",IF(AND(L59<>"",ISBLANK(J59),ISBLANK(K59)),"N/A","not answered/error"))) -> not answered/error | Q59: Document identification name: code: revision: date: Parameters mentioned in the criteria are: -XXXX -XXXX -XXXX that are monitored with respective frequence and place of sampling.
A60: IFA | B60: IFA v6 Smart | C60: AQ | D60: AQ-Smart 06.03.02 | E60: AQ 06 ENVIRONMENTAL AND BIODIVERSITY MANAGEMENT | F60: A biodiversity-inclusive environmental management plan (EMP) has been developed, setting out strategies to minimize all effects on the environment. | G60: An EMP, including biodiversity and based on the environmental impact assessment (EIA) in AQ 06.03.01 and the risk assessment in AQ 01.02.01, shall have been developed, setting out strategies to minimize all effects on the environment. It shall incorporate a regular environmental monitoring program, including the frequency of the parameters established to be measured. The records of disposal and emission shall demonstrate both legal compliance and accordance with the biosecurity plan (refer to AQ 20.08.01). Refer to guideline AQ III, “Environmental parameters of relevance based on the aquaculture system used,” where detailed guidance based on farming systems is provided. No “N/A.” | I60: Major Must | M60: =IF(AND(J60<>"",ISBLANK(K60),ISBLANK(L60)),"Yes",IF(AND(K60<>"",ISBLANK(J60),ISBLANK(L60)),"No",IF(AND(L60<>"",ISBLANK(J60),ISBLANK(K60)),"N/A","not answered/error"))) -> not answered/error | Q60: Document identification name: code: revision: date: Parameters mentioned in the criteria are: -XXXX -XXXX -XXXX that are monitored with respective frequence and place of sampling.
A61: IFA | B61: IFA v6 Smart | C61: AQ | D61: AQ-Smart 06.03.03 | E61: AQ 06 ENVIRONMENTAL AND BIODIVERSITY MANAGEMENT | F61: There is no significant negative impact on the biodiversity of the benthic fauna and/or recipient water body sediment/water column. | G61: For all farming systems, monitoring of benthic biodiversity, chemical indicators, and possible accumulation of chemical residues or organic waste in the recipient water body sediment shall take place. Type of analysis and monitoring frequency shall be determined based on the risks identified in the environmental impact assessment (EIA) (refer to AQ 06.03.01) and applicable legislation. Analysis results shall be available for the certification body (CB) audit, and the evidence provided shall show that there is no significant negative impact on the biodiversity of the benthic fauna and/or recipient water body sediment/water column. If a farmer considers that they may be exempted from benthic monitoring (e.g., due to the type of seabed substrate or water depth), they shall present evidence to support this position. | I61: Major Must | M61: =IF(AND(J61<>"",ISBLANK(K61),ISBLANK(L61)),"Yes",IF(AND(K61<>"",ISBLANK(J61),ISBLANK(L61)),"No",IF(AND(L61<>"",ISBLANK(J61),ISBLANK(K61)),"N/A","not answered/error"))) -> not answered/error | Q61: Document identification name: code: revision: date: If exists, describe the analysis results showing that there is no significant negative impact on the biodiversity of the benthic fauna and/or recipient water body sediment/water column.
A62: IFA | B62: IFA v6 Smart | C62: AQ | D62: AQ-Smart 06.03.04 | E62: AQ 06 ENVIRONMENTAL AND BIODIVERSITY MANAGEMENT | F62: There is further evaluation to show that there is no significant negative impact on the biodiversity of the benthic fauna and/or recipient water body sediment/water column. | G62: A biological quality evaluation based on macro fauna should provide insight on the potential impact. As a precautionary rule, effluents shall be treated before discharge. | I62: Recommendation | M62: =IF(AND(J62<>"",ISBLANK(K62),ISBLANK(L62)),"Yes",IF(AND(K62<>"",ISBLANK(J62),ISBLANK(L62)),"No",IF(AND(L62<>"",ISBLANK(J62),ISBLANK(K62)),"N/A","not answered/error"))) -> not answered/error
A63: IFA | B63: IFA v6 Smart | C63: AQ | D63: AQ-Smart 06.04.01 | E63: AQ 06 ENVIRONMENTAL AND BIODIVERSITY MANAGEMENT | F63: Water abstraction and discharge meet the requirements set by the competent authority and do not pose a risk to local communities and natural biodiversity. | G63: The records of discharge licenses and abstraction rights for each site, plus records of abstraction amounts taken over 12 months, shall be available. The producer shall show evidence that the farming activities do not pose a risk to desiccation-sensitive biodiversity and do not limit access to household water for the local community. | I63: Major Must | M63: =IF(AND(J63<>"",ISBLANK(K63),ISBLANK(L63)),"Yes",IF(AND(K63<>"",ISBLANK(J63),ISBLANK(L63)),"No",IF(AND(L63<>"",ISBLANK(J63),ISBLANK(K63)),"N/A","not answered/error"))) -> not answered/error | Q63: Document identification name: code: revision: date: Record specific restrictions checked and complied with:
A64: IFA | B64: IFA v6 Smart | C64: AQ | D64: AQ-Smart 06.04.02 | E64: AQ 06 ENVIRONMENTAL AND BIODIVERSITY MANAGEMENT | F64: The communities surrounding the farm have access to fishing areas, where applicable. | G64: The producer shall show evidence by means of documents (maps, official authorizations, licenses, regulations, stakeholder consultation, etc.) that communities are allowed to fish in a well-defined area around the aquaculture infrastructures (net cages, rope cultures, inlet pumping stations, etc.). | I64: Major Must | M64: =IF(AND(J64<>"",ISBLANK(K64),ISBLANK(L64)),"Yes",IF(AND(K64<>"",ISBLANK(J64),ISBLANK(L64)),"No",IF(AND(L64<>"",ISBLANK(J64),ISBLANK(K64)),"N/A","not answered/error"))) -> not answered/error
A65: IFA | B65: IFA v6 Smart | C65: AQ | D65: AQ-Smart 06.04.03 | E65: AQ 06 ENVIRONMENTAL AND BIODIVERSITY MANAGEMENT | F65: Inlet/outlet water quality is in compliance with existing local regulations and requirements of the environmental impact assessment (EIA)/environmental management plan (EMP). | G65: The sampling results, sampling plan (frequency and location of where samples are taken), and records of appropriate corrective actions following evaluation of inlet/outlet water quality shall be available for the certification body (CB) audit. Refer to guideline AQ III, “Environmental parameters of relevance based on the aquaculture system used.” | I65: Major Must | M65: =IF(AND(J65<>"",ISBLANK(K65),ISBLANK(L65)),"Yes",IF(AND(K65<>"",ISBLANK(J65),ISBLANK(L65)),"No",IF(AND(L65<>"",ISBLANK(J65),ISBLANK(K65)),"N/A","not answered/error"))) -> not answered/error | Q65: Sampling plan and results for inlet water Document identification name: code: revision: date: Sampling plan and results for outlet water based on the EIA (AQ 06.03.01) Document identification name: code: revision: date:
A66: IFA | B66: IFA v6 Smart | C66: AQ | D66: AQ-Smart 06.04.04 | E66: AQ 06 ENVIRONMENTAL AND BIODIVERSITY MANAGEMENT | F66: Fresh groundwater and/or potable water is not used to lower the salt concentration of farm water. | G66: Well water or potable water should not be used to lower the salt concentration of farm water. | I66: Recommendation | M66: =IF(AND(J66<>"",ISBLANK(K66),ISBLANK(L66)),"Yes",IF(AND(K66<>"",ISBLANK(J66),ISBLANK(L66)),"No",IF(AND(L66<>"",ISBLANK(J66),ISBLANK(K66)),"N/A","not answered/error"))) -> not answered/error
A67: IFA | B67: IFA v6 Smart | C67: AQ | D67: AQ-Smart 06.04.05 | E67: AQ 06 ENVIRONMENTAL AND BIODIVERSITY MANAGEMENT | F67: Water quality – in all storage systems – is verified as adequate for its uses. | G67: Indoor primary production facilities and any other water storage systems shall maintain a supply of water fit for its intended purposes. The water in all storage systems shall not compromise food safety, handwashing, equipment, and post-harvest washing. | I67: Major Must | M67: =IF(AND(J67<>"",ISBLANK(K67),ISBLANK(L67)),"Yes",IF(AND(K67<>"",ISBLANK(J67),ISBLANK(L67)),"No",IF(AND(L67<>"",ISBLANK(J67),ISBLANK(K67)),"N/A","not answered/error"))) -> not answered/error | Q67: Description of water storage system. Records of cleaning and maintenance.
A68: IFA | B68: IFA v6 Smart | C68: AQ | D68: AQ-Smart 06.04.06 | E68: AQ 06 ENVIRONMENTAL AND BIODIVERSITY MANAGEMENT | F68: Measured impacts of effluents are in accordance with legislation and with the prescriptions of the environmental impact assessment (EIA)/environmental management plan (EMP). | G68: It is the responsibility of the producer to ensure that no process impacting the recipient water exceeds targets in the EMP. Farm management shall be able to demonstrate compliance and knowledge of legislation in the interview. The records and discharge permits, which shall be valid and operating within limits at each site, shall be in place. It shall be possible to monitor progress. | I68: Major Must | M68: =IF(AND(J68<>"",ISBLANK(K68),ISBLANK(L68)),"Yes",IF(AND(K68<>"",ISBLANK(J68),ISBLANK(L68)),"No",IF(AND(L68<>"",ISBLANK(J68),ISBLANK(K68)),"N/A","not answered/error"))) -> not answered/error | Q68: Verification to be done together with AQ 06.04.03.
A69: IFA | B69: IFA v6 Smart | C69: AQ | D69: AQ-Smart 07.01.01 | E69: AQ 07 CONSERVATION | F69: The producer has a wildlife management and conservation plan that acknowledges the impact of farming activities (including possible escapes) on the environment. | G69: There shall be a documented action plan that aims to enhance habitats and maintain biodiversity, aiming for zero escapes. This can be either an individual plan or a regional activity that the farm participates in or is covered by. The action plan shall pay special attention to areas of environmental interest being protected and make reference to legal requirements, where applicable. | I69: Major Must | M69: =IF(AND(J69<>"",ISBLANK(K69),ISBLANK(L69)),"Yes",IF(AND(K69<>"",ISBLANK(J69),ISBLANK(L69)),"No",IF(AND(L69<>"",ISBLANK(J69),ISBLANK(K69)),"N/A","not answered/error"))) -> not answered/error
A70: IFA | B70: IFA v6 Smart | C70: AQ | D70: AQ-Smart 07.01.02 | E70: AQ 07 CONSERVATION | F70: The producer considers how to enhance the environment for the benefit of the local community and flora and fauna with a policy that is compatible with sustainable commercial aquaculture production, striving to minimize environmental impact. | G70: There should be tangible actions and initiatives that can be demonstrated: 1) By the producer on the production site, at local scale, or at regional scale 2) By participation in a group that is active in environmental support schemes concerned with habitat quality and habitat elements. There should be a commitment within the conservation plan to conduct a baseline evaluation of the current levels, location, condition, etc. of the fauna and flora on the farm, so as to enable actions to be planned. Within the conservation plan, there should also be a clear list of priorities and actions for enhancing habitats for fauna and flora where viable and for increasing biodiversity on the farm. | I70: Recommendation | M70: =IF(AND(J70<>"",ISBLANK(K70),ISBLANK(L70)),"Yes",IF(AND(K70<>"",ISBLANK(J70),ISBLANK(L70)),"No",IF(AND(L70<>"",ISBLANK(J70),ISBLANK(K70)),"N/A","not answered/error"))) -> not answered/error
A71: IFA | B71: IFA v6 Smart | C71: AQ | D71: AQ-Smart 07.02.01 | E71: AQ 07 CONSERVATION | F71: The producer performs a risk assessment to evaluate whether predator preventive nets are required. | G71: A risk assessment shall be performed, with results determining whether predator nets may be required, which size would restrict access to the farmed stock, and how to avoid entanglement of the farmed aquatic species. Refer to AQ 20.02.14 on risk assessment for animal welfare. | I71: Major Must | M71: =IF(AND(J71<>"",ISBLANK(K71),ISBLANK(L71)),"Yes",IF(AND(K71<>"",ISBLANK(J71),ISBLANK(L71)),"No",IF(AND(L71<>"",ISBLANK(J71),ISBLANK(K71)),"N/A","not answered/error"))) -> not answered/error | Q71: Document identification name: code: revision: date:
A72: IFA | B72: IFA v6 Smart | C72: AQ | D72: AQ-Smart 07.02.02 | E72: AQ 07 CONSERVATION | F72: If nets are required, there is in place a regular net and predator net checking system used to reduce negative interaction with the wildlife. | G72: The records and management system for nets shall be in place to prove that they exist and operate to reduce negative interactions with the wildlife. Interviews with workers shall be taken in account for justified records. | I72: Major Must | M72: =IF(AND(J72<>"",ISBLANK(K72),ISBLANK(L72)),"Yes",IF(AND(K72<>"",ISBLANK(J72),ISBLANK(L72)),"No",IF(AND(L72<>"",ISBLANK(J72),ISBLANK(K72)),"N/A","not answered/error"))) -> not answered/error
A73: IFA | B73: IFA v6 Smart | C73: AQ | D73: AQ-Smart 07.02.03 | E73: AQ 07 CONSERVATION | F73: Implemented predator control techniques avoid any type of lethal interaction with the wildlife. | G73: An effective predator control plan shall be in place, using exclusion measures and/or scaring devices. Documented anti-predator methods shall be in accordance with relevant legislation and codes of practice, including legislation on endangered species. If all nonlethal control options have been exhausted, lethal dispatch of predators (if workers’ safety is in danger, to avoid significant suffering or mortality among farmed aquatic species, as an act of mercy, etc.) is within the constraints of legislation. The producer shall record all lethal dispatches of predators (number of animals and species). A legal permit allowing lethal dispatch shall be available. Lethal dispatch of predators shall be performed humanely. | I73: Major Must | M73: =IF(AND(J73<>"",ISBLANK(K73),ISBLANK(L73)),"Yes",IF(AND(K73<>"",ISBLANK(J73),ISBLANK(L73)),"No",IF(AND(L73<>"",ISBLANK(J73),ISBLANK(K73)),"N/A","not answered/error"))) -> not answered/error | Q73: Document identification name: code: revision: date:
A74: IFA | B74: IFA v6 Smart | C74: AQ | D74: AQ-Smart 07.03.01 | E74: AQ 07 CONSERVATION | F74: The environmental management plan (EMP) includes a contingency plan and a standard operating procedure to avoid escape of farmed aquatic species into the sea or local freshwater course. | G74: Procedures to avoid escapes shall be in place, paying special attention to climate change and taking into account site history. - Precautions shall be in place to prevent the erosion of dams or channels that could lead to subsequent escapes. - The infrastructure shall be calculated for high flood levels. Evidence of high flood levels in calculations shall be presented. - Additional infrastructure to prevent escapes shall be part of the preventive measures. - The EMP shall include a contingency plan. The contingency plans and records of all escaped stock for the previous certification cycle shall be available, along with confirmation that all escapes have been reported to the authorities for all sites. Information reported to the authorities shall include biomass, health status, and any food safety risk associated with the escaped farmed aquatic species. The hatchery/farm shall have an effective and documented procedure for preventing accidental release of the farmed aquatic species into the environment. Where applicable, pen structures and moorings shall be inspected according to a documented schedule based on the risk assessment. Routine maintenance, and repair procedures as necessary, shall be performed and recorded. Contingency plans should include plans for recapturing escaped farmed aquatic species. | I74: Major Must | M74: =IF(AND(J74<>"",ISBLANK(K74),ISBLANK(L74)),"Yes",IF(AND(K74<>"",ISBLANK(J74),ISBLANK(L74)),"No",IF(AND(L74<>"",ISBLANK(J74),ISBLANK(K74)),"N/A","not answered/error"))) -> not answered/error | Q74: Document identification of escapes in the previous certification cycle name: code: revision: date: If escapes took place, evidence that this has been reported to the authorities Ref. XXXX
A75: IFA | B75: IFA v6 Smart | C75: AQ | D75: AQ-Smart 07.04.01 | E75: AQ 07 CONSERVATION | F75: The sites or related facilities have not been established within a designated national protected area (PA), in PAs with The International Union for Conservation of Nature (IUCN) categories Ia, “Strict Nature Reserve” through to IV, “Habitat/Species Management Area,” or in areas defined under international conventions (such as Ramsar or World Heritage). If farm facilities are within PA IUCN category V or VI, consent of the PA management is required. | G75: There shall be evidence that the farm site or related facilities are not within a PA. “The World Database on Protected Areas (WDPA)” is the most complete compilation of protected areas data available. The datasets are available as free downloads at http://www.protectedplanet.net. Evidence shall include: geographic location provided at registration. If present within PA category V or VI, the certification body (CB) auditor shall contact PA authorities to establish if the site is in line with the management objectives of the PA. Information shall be made public. See guideline AQ IV, “The Ramsar convention on wetlands.” | I75: Major Must | M75: =IF(AND(J75<>"",ISBLANK(K75),ISBLANK(L75)),"Yes",IF(AND(K75<>"",ISBLANK(J75),ISBLANK(L75)),"No",IF(AND(L75<>"",ISBLANK(J75),ISBLANK(K75)),"N/A","not answered/error"))) -> not answered/error | Q75: Evidence that the farm site or related facilities are not within a PA: -XXXX Confirm the geo-coordinates and the date of the last verification (date: XXXX)
A76: IFA | B76: IFA v6 Smart | C76: AQ | D76: AQ-Smart 07.04.02 | E76: AQ 07 CONSERVATION | F76: New ponds, sites, or related facilities have not been established (before April 2008) in areas that were previously within a mangrove ecosystem, within the natural intertidal zone, or a high conservation value area. | G76: If the farm facilities were built after April 2008, there shall be evidence that the area was not previously part of a mangrove ecosystem, within the natural intertidal zone, or a high conservation value area (categories I–IV) before April 2008. Evidence shall be checked within the environmental impact assessment (EIA) (including biodiversity) and shall include: record of land use/status and habitat types prior to farm building, presence/absence of IUCN red list species, remote sensing/satellite imagery. The information shall be made public. | I76: Major Must | M76: =IF(AND(J76<>"",ISBLANK(K76),ISBLANK(L76)),"Yes",IF(AND(K76<>"",ISBLANK(J76),ISBLANK(L76)),"No",IF(AND(L76<>"",ISBLANK(J76),ISBLANK(K76)),"N/A","not answered/error"))) -> not answered/error | Q76: Document identification name: code: revision: date: Date of the farm site establishment XXXX, the prior land use/status was: XXXX, habitat types XXXX, and the source of information is XXXX.
A77: IFA | B77: IFA v6 Smart | C77: AQ | D77: AQ-Smart 07.04.03 | E77: AQ 07 CONSERVATION | F77: Farms established between May 1999 and April 2008 within mangroves, the natural intertidal zone, or a high conservation value area show evidence that they are in the process of being retired, rehabilitating the area, and, if necessary, compensating surrounding communities. From the date of first certification, a maximum of three years is allowed to complete the retirement and rehabilitation process, after which new locations (if any, outside these areas) may be considered for certification. | G77: There shall be a documented rehabilitation plan containing at least the objective(s), time frame, means, activities, expected output, and financing and compensation provisions in agreement with local communities. Evidence of recent funding of rehabilitation (plans) shall be available. The information shall be made public. Refer to the Convention on Wetlands (Ramsar) – Resolution VII.21, “Enhancing the conservation and wise use of intertidal wetlands” (adopted at the seventh Meeting of the Conference of the Contracting Parties to the Convention on Wetlands, San José, Costa Rica, 10–18 May 1999), article 15, “Contracting Parties to suspend the promotion, creation of new facilities, and expansion of unsustainable aquaculture activities harmful to coastal wetlands.” | I77: Major Must | M77: =IF(AND(J77<>"",ISBLANK(K77),ISBLANK(L77)),"Yes",IF(AND(K77<>"",ISBLANK(J77),ISBLANK(L77)),"No",IF(AND(L77<>"",ISBLANK(J77),ISBLANK(K77)),"N/A","not answered/error"))) -> not answered/error | Q77: Document identification name: code: revision: date: Date of the farm site establishment XXXX. If apply, describe the rehabilitation plan (objective, time frame, means, activities, expected output, financing and compensation provisions in agreement with local communities).
A78: IFA | B78: IFA v6 Smart | C78: AQ | D78: AQ-Smart 07.04.04 | E78: AQ 07 CONSERVATION | F78: Farms within the intertidal zone, mangrove, or high conservation value areas improve the environment through management and restoration, retiring non-compliant ponds, and increasing productivity of remaining farm areas above the intertidal zone. | G78: There shall be in place a documented restoration plan containing at least the objective(s), means, activities, expected output, and financing and compensation provisions in agreement with local communities. Evidence of recent funding of restoration (plans) shall be available if operations are in mangroves or intertidal zones. | I78: Major Must | M78: =IF(AND(J78<>"",ISBLANK(K78),ISBLANK(L78)),"Yes",IF(AND(K78<>"",ISBLANK(J78),ISBLANK(L78)),"No",IF(AND(L78<>"",ISBLANK(J78),ISBLANK(K78)),"N/A","not answered/error"))) -> not answered/error | Q78: Document identification name: code: revision: date:
A79: IFA | B79: IFA v6 Smart | C79: AQ | D79: AQ-Smart 07.04.05 | E79: AQ 07 CONSERVATION | F79: Mangroves are removed under prescribed purposes only. | G79: The removal of mangrove vegetation shall be allowed only for channels or piping that service sites above the intertidal zones, and when official permits of the public sector have been granted and a rehabilitation plan is part of the permit. Restoration of removed mangroves shall be equal to or exceed the area removed and shall replicate the diversity of species removed. | I79: Major Must | M79: =IF(AND(J79<>"",ISBLANK(K79),ISBLANK(L79)),"Yes",IF(AND(K79<>"",ISBLANK(J79),ISBLANK(L79)),"No",IF(AND(L79<>"",ISBLANK(J79),ISBLANK(K79)),"N/A","not answered/error"))) -> not answered/error | Q79: Document identification name: code: revision: date: date of the official permit:
A80: IFA | B80: IFA v6 Smart | C80: AQ | D80: AQ-Smart 07.04.06 | E80: AQ 07 CONSERVATION | F80: There is a rehabilitation plan in place for when a site operation within mangroves or other sensitive ecosystems is retired. | G80: There shall be in place a documented rehabilitation plan for when operations in mangroves or other sensitive ecosystems are retired. The plan shall contain at least objective(s), means, activities, expected output and financing. Restoration of removed mangroves shall be equal to or exceed the area removed and shall replicate the diversity of species removed. | I80: Major Must | M80: =IF(AND(J80<>"",ISBLANK(K80),ISBLANK(L80)),"Yes",IF(AND(K80<>"",ISBLANK(J80),ISBLANK(L80)),"No",IF(AND(L80<>"",ISBLANK(J80),ISBLANK(K80)),"N/A","not answered/error"))) -> not answered/error | Q80: Document identification name: code: revision: date:
A81: IFA | B81: IFA v6 Smart | C81: AQ | D81: AQ-Smart 07.05.01 | E81: AQ 07 CONSERVATION | F81: Consideration has been given to the conversion of unproductive sites. | G81: There should be a plan to convert unproductive sites and identified ecologically prioritized areas (low-lying wetlands, woodlands, headland strips, or areas of impoverished soil, etc.) into conservation areas, where viable, or into ecological focus areas for the encouragement of natural flora and fauna. | I81: Recommendation | M81: =IF(AND(J81<>"",ISBLANK(K81),ISBLANK(L81)),"Yes",IF(AND(K81<>"",ISBLANK(J81),ISBLANK(L81)),"No",IF(AND(L81<>"",ISBLANK(J81),ISBLANK(K81)),"N/A","not answered/error"))) -> not answered/error
A82: IFA | B82: IFA v6 Smart | C82: AQ | D82: AQ-Smart 07.06.01 | E82: AQ 07 CONSERVATION | F82: On-farm energy use is monitored. | G82: There shall be records of on-farm energy use (e.g., invoices detailing energy consumption). The producer shall be aware of where and how energy is consumed on the farm and through farming practices. Trend analysis of energy use shall be available (listed per cycle and per biomass). | I82: Minor Must | M82: =IF(AND(J82<>"",ISBLANK(K82),ISBLANK(L82)),"Yes",IF(AND(K82<>"",ISBLANK(J82),ISBLANK(L82)),"No",IF(AND(L82<>"",ISBLANK(J82),ISBLANK(K82)),"N/A","not answered/error"))) -> not answered/error
A83: IFA | B83: IFA v6 Smart | C83: AQ | D83: AQ-Smart 07.06.02 | E83: AQ 07 CONSERVATION | F83: Based on the results of the monitoring, there is a plan to improve energy efficiency on the farm. | G83: A documented plan identifying opportunities to improve energy efficiency shall be available (implementing insulation where needed, revising transport planning to optimize use of energy, etc.). | I83: Minor Must | M83: =IF(AND(J83<>"",ISBLANK(K83),ISBLANK(L83)),"Yes",IF(AND(K83<>"",ISBLANK(J83),ISBLANK(L83)),"No",IF(AND(L83<>"",ISBLANK(J83),ISBLANK(K83)),"N/A","not answered/error"))) -> not answered/error | Q83: Document identification name: code: revision: date:
A84: IFA | B84: IFA v6 Smart | C84: AQ | D84: AQ-Smart 07.06.03 | E84: AQ 07 CONSERVATION | F84: The plan to improve energy efficiency considers minimizing the use of nonrenewable energy where possible. | G84: The producer shall consider reducing the use of nonrenewable energy to the lowest possible and using renewable energy instead. Identification of renewable energy sourcing possibilities shall be available. The use of wood chips shall be taken with caution, as no forests shall be cut to produce them. | I84: Minor Must | M84: =IF(AND(J84<>"",ISBLANK(K84),ISBLANK(L84)),"Yes",IF(AND(K84<>"",ISBLANK(J84),ISBLANK(L84)),"No",IF(AND(L84<>"",ISBLANK(J84),ISBLANK(K84)),"N/A","not answered/error"))) -> not answered/error
A85: IFA | B85: IFA v6 Smart | C85: AQ | D85: AQ-Smart 08.01 | E85: AQ 08 COMPLAINTS | F85: A complaint procedure relating to both internal and external issues covered by the standard is available and implemented. | G85: A documented complaint procedure shall be available to facilitate the recording and follow-up of all received complaints relating to issues covered by the standard and to record actions taken with respect to such complaints. In the case of producer groups, the producer group members do not need the complete complaint procedure, but only the parts that are relevant to them. If the producer is informed by a competent and or local authority that they are under investigation and/or has received a sanction within the scope of the certification, the complaint procedure shall require the producer to notify the GLOBALG.A.P. Secretariat via the certification body (CB). In the case of complaints related to the standard (food safety, workers’ well-being, environmental protection, animal welfare, etc.) that can endanger the reputation and credibility of the GLOBALG.A.P. brand, the certificate holder shall inform the CB immediately. No “N/A.” | I85: Major Must | M85: =IF(AND(J85<>"",ISBLANK(K85),ISBLANK(L85)),"Yes",IF(AND(K85<>"",ISBLANK(J85),ISBLANK(L85)),"No",IF(AND(L85<>"",ISBLANK(J85),ISBLANK(K85)),"N/A","not answered/error"))) -> not answered/error | Q85: Document identification name: code: revision: date:
A86: IFA | B86: IFA v6 Smart | C86: AQ | D86: AQ-Smart 09.01 | E86: AQ 09 RECALL AND WITHDRAWAL PROCEDURE | F86: Documented procedures are in place to manage the recall and withdrawal of products originating from certified production processes from the marketplace, and such procedures are tested annually. | G86: The producer shall have a documented procedure that identifies: - The types of events that may result in a recall and withdrawal - The persons responsible for making decisions on the possible recall and withdrawal - The mechanism for notifying the next step in the supply chain - The notification of relevant authorities when required - Steps taken to contact the certification body (CB), which in turn may contact the GLOBALG.A.P. Secretariat - The methods for reconciling stock The procedure shall be tested annually for effectiveness and the results of the mock recall shall be recorded (e.g., selecting a lot and demonstrating that it can be effectively traced forward to the customer). Actual communications of the mock recall to the clients are not necessary. An up-to-date list of telephone numbers and email addresses is sufficient. If an actual recall and withdrawal occurred during the past year, documentation of these shall be provided for compliance. | I86: Major Must | M86: =IF(AND(J86<>"",ISBLANK(K86),ISBLANK(L86)),"Yes",IF(AND(K86<>"",ISBLANK(J86),ISBLANK(L86)),"No",IF(AND(L86<>"",ISBLANK(J86),ISBLANK(K86)),"N/A","not answered/error"))) -> not answered/error | Q86: Recall and withdrawal procedure name: code: revision: date: Date of mock recall test:XXX Name of product XXX and batch XXX date involved in the mock recall test: XXX Documented procedures are in place to effectively manage the withdrawal of registered products.
A87: IFA | B87: IFA v6 Smart | C87: AQ | D87: AQ-Smart 10.01 | E87: AQ 10 FOOD DEFENSE | F87: A food defense system is in place to address risks associated with malicious attack or contamination. | G87: The system shall include: - A risk assessment to identify potential threats to the safety of products, taking into account risks from deliberate attempt to inflict contamination or damage - A documented food defense plan to specify the measures to control any risks identified in the risk assessment - Consideration of identification of tampering to the premises and products, monitoring of external storage and intake points, controlled access where relevant, receiving inputs from safe sources, and having available information for all employees and subcontractors - Worker, visitor, and subcontractor awareness of the need to support food defense measures, ensured through training, signs, pictograms, etc. | I87: Major Must | M87: =IF(AND(J87<>"",ISBLANK(K87),ISBLANK(L87)),"Yes",IF(AND(K87<>"",ISBLANK(J87),ISBLANK(L87)),"No",IF(AND(L87<>"",ISBLANK(J87),ISBLANK(K87)),"N/A","not answered/error"))) -> not answered/error | Q87: FOOD DEFENSE Plan: XXX dated_ XX rev_XXX
A88: IFA | B88: IFA v6 Smart | C88: AQ | D88: AQ-Smart 11.01 | E88: AQ 11 GLOBALG.A.P. STATUS | F88: Transaction documentation includes reference to the GLOBALG.A.P. status and the GLOBALG.A.P. Number (GGN). | G88: Delivery notes, sales invoices, and, where appropriate, other documentation related to sales of products originating from certified production processes shall include the GGN of the certificate holder and a reference to the GLOBALG.A.P. certification status. This is not obligatory in internal documentation. Positive identification of the certification status is sufficient on transaction documentation (e.g., “GLOBALG.A.P. certified <product name>”). Products from noncertified production processes do not to be identified as “noncertified.” Indication of the certification status is obligatory regardless of whether the product from a certified production process was sold as such or not. This cannot be checked during the initial (first ever) certification body (CB) audit because the producer does not yet have certification and the producer cannot reference the GLOBALG.A.P. certification status before the first positive certification decision. “N/A” only if there is an up-to-date and documented bilateral agreement available between the certificate holder and their direct buyer that all shipments contain only products originating from certified production processes. | I88: Major Must | M88: =IF(AND(J88<>"",ISBLANK(K88),ISBLANK(L88)),"Yes",IF(AND(K88<>"",ISBLANK(J88),ISBLANK(L88)),"No",IF(AND(L88<>"",ISBLANK(J88),ISBLANK(K88)),"N/A","not answered/error"))) -> not answered/error | Q88: Indicate the GLOBALG.A.P. certification status and GGN used, how it is used, the type of transaction record checked, the reference number, and the date. In the case of an initial audit, write: “N/A. Initial audit.”
A89: IFA | B89: IFA v6 Smart | C89: AQ | D89: AQ-Smart 12.01 | E89: AQ 12 LOGO USE | F89: The GLOBALG.A.P. word, trademark, and QR code or logo, as well as the GLOBALG.A.P. Number (GGN) are used according to “GLOBALG.A.P. trademarks use: Policy and guidelines.” | G89: The producer shall use the GLOBALG.A.P. word, trademark, and QR code or logo, as well as the GGN, Global Location Number (GLN), or sub-GLN according to “GLOBALG.A.P. trademarks use: Policy and guidelines.” The GLOBALG.A.P. word, trademark, or logo shall never appear on the final product, on the consumer packaging, or at the point of sale. However, the certificate holder can use any and/or all in business-to-business communications. “N/A” for compound feed or GLOBALG.A.P. aquaculture ova or seedlings when not intended for sale to final consumers and definitely not appearing at any point of sale to final consumers. The GLOBALG.A.P. word, trademark, or logo cannot be in use during the initial (first ever) certification body (CB) audit because the producer does not yet have certification, and the producer cannot refer to the GLOBALG.A.P. certification status before the first positive certification decision. | I89: Major Must | M89: =IF(AND(J89<>"",ISBLANK(K89),ISBLANK(L89)),"Yes",IF(AND(K89<>"",ISBLANK(J89),ISBLANK(L89)),"No",IF(AND(L89<>"",ISBLANK(J89),ISBLANK(K89)),"N/A","not answered/error"))) -> not answered/error | Q89: Record where the GLOBALG.A.P. trademarks/logos are used by the producer.
A90: IFA | B90: IFA v6 Smart | C90: AQ | D90: AQ-Smart 13.01 | E90: AQ 13 PARALLEL OWNERSHIP | F90: An effective system is in place to identify all products originating from GLOBALG.A.P. certified processes and segregate them from products originating from noncertified processes. | G90: A system shall be in place to avoid mixing products originating from certified and noncertified production processes. This can be done via physical identification or product handling procedures, including the relevant records. | I90: Major Must | M90: =IF(AND(J90<>"",ISBLANK(K90),ISBLANK(L90)),"Yes",IF(AND(K90<>"",ISBLANK(J90),ISBLANK(L90)),"No",IF(AND(L90<>"",ISBLANK(J90),ISBLANK(K90)),"N/A","not answered/error"))) -> not answered/error | Q90: All product is originating from certified production process.///// - On-site verification has been conducted for Segregation and Product Identification for the Product XXXXX, with Lot/Batch Number XXXXX, throughout operational activities and in accordance with the product flow
A91: IFA | B91: IFA v6 Smart | C91: AQ | D91: AQ-Smart 13.02 | E91: AQ 13 PARALLEL OWNERSHIP | F91: The GLOBALG.A.P. Number (GGN) is indicated on all final products originating from certified production processes when registered for parallel ownership. | G91: For producers registered for parallel ownership (where products originating from certified and noncertified production processes are produced and/or owned by one legal entity), there shall be a system to ensure that all final products from a certified production process are correctly identified. Products originating from a certified production process, including those packed in final consumer packaging (either from farm level or after product handling) shall be identified with the GGN. It can be the GGN of the Option 2 producer group, the GGN of the producer group member, both GGNs, or the GGN of the Option 1 individual producer. The GGN shall not be used to label products originating from noncertified production processes. “N/A” only if the producer owns only products from GLOBALG.A.P. certified production processes, or if there is a documented agreement available between the producer and the client not to use the GGN, Global Location Number (GLN), or sub-GLN on the sale-ready product. This can also be the client’s own label specifications where the GGN is not included. | I91: Major Must | M91: =IF(AND(J91<>"",ISBLANK(K91),ISBLANK(L91)),"Yes",IF(AND(K91<>"",ISBLANK(J91),ISBLANK(L91)),"No",IF(AND(L91<>"",ISBLANK(J91),ISBLANK(K91)),"N/A","not answered/error"))) -> not answered/error | Q91: All product is originating from certified production process. ////// -- Not All All product is originating form certified production process.On the site, a sample of final product of XXXXXX labeled with a GGN XXXXXX ; LOT/Batch : XXXXX has been carefully selected and trace it back to its origin to confirm the certification status. If Option 2 (producer group member/certificate holder/both), GGN used for identification:
A92: IFA | B92: IFA v6 Smart | C92: AQ | D92: AQ-Smart 13.03 | E92: AQ 13 PARALLEL OWNERSHIP | F92: A final verification step is in place to ensure correct dispatch of products originating from certified and noncertified production processes. | G92: The check shall be documented to show that the products are correctly identified and dispatched according to certified or noncertified status of their production processes. | I92: Major Must | M92: =IF(AND(J92<>"",ISBLANK(K92),ISBLANK(L92)),"Yes",IF(AND(K92<>"",ISBLANK(J92),ISBLANK(L92)),"No",IF(AND(L92<>"",ISBLANK(J92),ISBLANK(K92)),"N/A","not answered/error"))) -> not answered/error | Q92: All product is originating from certified production process. ///Not All All product is originating form certified production process. Check records XXX. and/or Interview person responsible for final check name: XXXXX
A93: IFA | B93: IFA v6 Smart | C93: AQ | D93: AQ-Smart 13.04 | E93: AQ 13 PARALLEL OWNERSHIP | F93: Products that are purchased from different sources are identified. | G93: Procedures shall be established, documented, and maintained, appropriate to the scale of the operation, for identifying quantities of products originating from certified and, where applicable, noncertified production processes purchased from different sources (i.e., other producers or traders) for all registered products. Records shall include: - Product description - GLOBALG.A.P. certification status - Quantities of product(s) purchased - Supplier details - Copy of the GLOBALG.A.P. certificates, where applicable - Traceability data/codes related to the purchased products - Purchase orders and/or invoices received - List of approved suppliers | I93: Major Must | M93: =IF(AND(J93<>"",ISBLANK(K93),ISBLANK(L93)),"Yes",IF(AND(K93<>"",ISBLANK(J93),ISBLANK(L93)),"No",IF(AND(L93<>"",ISBLANK(J93),ISBLANK(K93)),"N/A","not answered/error"))) -> not answered/error | Q93: All product is originating form certified production process. /// Not All All product is originating form certified production process. It is take undercontrol by the Procedure XXX dated DD/MM/YY.Conducted a visual inspection to ensure that all incoming and stored products are appropriately identified, in accordance with the established procedure Name of purchased product:XXX batch:XXX date checked:XXX GLOBALG.A.P. certification status: XXX Quantities of product(s) purchased:XXX Supplier details:XXX Copy of the GLOBALG.A.P. certificates:XXX Traceability data/codes related to the purchased products:XXX Purchase orders and/or invoices received: List of approved suppliers: XXX
A94: IFA | B94: IFA v6 Smart | C94: AQ | D94: AQ-Smart 13.05 | E94: AQ 13 PARALLEL OWNERSHIP | F94: A documented test of the traceability system is conducted annually. | G94: A documented test of the traceability system shall be conducted annually. This exercise may be included with the test of recall and withdrawal procedures, or may be carried out separately, depending on the type of production. | I94: Major Must | M94: =IF(AND(J94<>"",ISBLANK(K94),ISBLANK(L94)),"Yes",IF(AND(K94<>"",ISBLANK(J94),ISBLANK(L94)),"No",IF(AND(L94<>"",ISBLANK(J94),ISBLANK(K94)),"N/A","not answered/error"))) -> not answered/error | Q94: Document identification name: code: revision: date: Name of purchased product:XXX batch:XXX date checked:XXX
A95: IFA | B95: IFA v6 Smart | C95: AQ | D95: AQ-Smart 14.01 | E95: AQ 14 FARM MASS BALANCE | F95: Sales records are available for all quantities sold for all registered products. | G95: Sales details of the quantities of products originating from certified and, where applicable, noncertified production processes shall be recorded for all registered products, with particular attention to quantities sold and descriptions provided. The documents shall demonstrate the consistent balance between the input and the output of products originating from certified and noncertified production processes. No “N/A.” | I95: Major Must | M95: =IF(AND(J95<>"",ISBLANK(K95),ISBLANK(L95)),"Yes",IF(AND(K95<>"",ISBLANK(J95),ISBLANK(L95)),"No",IF(AND(L95<>"",ISBLANK(J95),ISBLANK(K95)),"N/A","not answered/error"))) -> not answered/error | Q95: Record one example each for all registered products. Name of product, batch/date checked Product Name #1: XXXX - Sales Record - Batch/DT Number XXXX - Product #2: XXXX - Sales Record - Batch/DT Number XXXX - Product #3: XXXX - Sales Record -Batch/ DT Number XXXX - .
A96: IFA | B96: IFA v6 Smart | C96: AQ | D96: AQ-Smart 14.02 | E96: AQ 14 FARM MASS BALANCE | F96: Quantities (produced, stored, and/or purchased) are recorded and summarized for all products. | G96: Quantities (including information on volumes or weight) of incoming (including purchased products), outgoing (including mortalities), and stored products (both from certified and, where applicable, from noncertified production processes) shall be recorded and a summary maintained for all registered products, so as to facilitate the mass balance verification process. The frequency of the mass balance verification shall be defined and be appropriate to the scale of the operation, but it shall be done at least annually for each product. Documents to demonstrate mass balance shall be clearly identified. This principle and the respective criteria apply to all producers applying for or maintaining GLOBALG.A.P. certification. No “N/A.” | I96: Major Must | M96: =IF(AND(J96<>"",ISBLANK(K96),ISBLANK(L96)),"Yes",IF(AND(K96<>"",ISBLANK(J96),ISBLANK(L96)),"No",IF(AND(L96<>"",ISBLANK(J96),ISBLANK(K96)),"N/A","not answered/error"))) -> not answered/error | Q96: Name of product (the mass balance exercise verified is per species specific): Record for at least one product, prioritizing main products and/or products under parallel ownership. Frequency of the mass balance calculation: XXXX. Name of product #1 : XXXX; - [product originating from certified production process] Quantity input: xxxxx; Quantity output: xxxx, unexplained loss: xxxxx; escape:xxxx, mortality:xxxxx, culling: xxxx, storage of product originating from certified production process; error deltax:xxxx; reson for the delta:xxxx (if applcable) product originating from NONcertified production process]: Quantity input: xxxxx; Quantity output: xxxx, unexplained loss: xxxxx; escape:xxxx, mortality:xxxxx, culling: xxxx, storage of product originating from NONcertified production process;error deltax:xxxx; reson for the delta:xxxx Name of product #2 : XXXX; - [product originating from certified production process] Quantity input: xxxxx; Quantity output: xxxx, unexplained loss: xxxxx; escape:xxxx, mortality:xxxxx, culling: xxxx, storage of product originating from certified production process; error deltax:xxxx; reson for the delta:xxxx (if applcable) product originating from NONcertified production process]: Quantity input: xxxxx; Quantity output: xxxx, unexplained loss: xxxxx; escape:xxxx, mortality:xxxxx, culling: xxxx, storage of product originating from NONcertified production process;error deltax:xxxx; reson for the delta:xxxx Name of product #3 : XXXX; - [product originating from certified production process] Quantity input: xxxxx; Quantity output: xxxx, unexplained loss: xxxxx; escape:xxxx, mortality:xxxxx, culling: xxxx, storage of product originating from certified production process; error deltax:xxxx; reson for the delta:xxxx (if applcable) product originating from NONcertified production process]: Quantity input: xxxxx; Quantity output: xxxx, unexplained loss: xxxxx; escape:xxxx, mortality:xxxxx, culling: xxxx, storage of product originating from NONcertified production process;error deltax:xxxx; reson for the delta:xxxx
... A114: IFA | B114: IFA v6 Smart | C114: AQ | D114: AQ-Smart 19.01.03 | E114: AQ 19 CHEMICAL COMPOUNDS | F114: All chemical compounds are demonstrably approved for aquaculture production processes. | G114: All chemical compounds shall be demonstrably approved for the use in aquaculture production processes in the country of production and destination. There shall be evidence of a risk assessment by a competent person where there is no legislation on specific chemical substances/active ingredients. | I114: Major Must | M114: =IF(AND(J114<>"",ISBLANK(K114),ISBLANK(L114)),"Yes",IF(AND(K114<>"",ISBLANK(J114),ISBLANK(L114)),"No",IF(AND(L114<>"",ISBLANK(J114),ISBLANK(K114)),"N/A","not answered/error"))) -> not answered/error | Q114: Verified in compliance through the AHP.
A115: IFA | B115: IFA v6 Smart | C115: AQ | D115: AQ-Smart 19.01.04 | E115: AQ 19 CHEMICAL COMPOUNDS | F115: Chemical compounds are stored in accordance with manufacturer instructions and legislation. | G115: Chemical compounds shall be stored in a secure lockable storage and in accordance with manufacturer instructions, legislation, and, where appropriate, be physically separated. Compliance shall require a visual assessment of the chemical store. No “N/A.” | I115: Major Must | M115: =IF(AND(J115<>"",ISBLANK(K115),ISBLANK(L115)),"Yes",IF(AND(K115<>"",ISBLANK(J115),ISBLANK(L115)),"No",IF(AND(L115<>"",ISBLANK(J115),ISBLANK(K115)),"N/A","not answered/error"))) -> not answered/error
A116: IFA | B116: IFA v6 Smart | C116: AQ | D116: AQ-Smart 19.01.05 | E116: AQ 19 CHEMICAL COMPOUNDS | F116: The chemical compound storage is kept locked and with access limited to workers with training. | G116: The chemical compound storage shall be kept locked at all times when not in use. Workers with access rights shall show evidence of training according to AQ 04.02.01. No “N/A.” | I116: Major Must | M116: =IF(AND(J116<>"",ISBLANK(K116),ISBLANK(L116)),"Yes",IF(AND(K116<>"",ISBLANK(J116),ISBLANK(L116)),"No",IF(AND(L116<>"",ISBLANK(J116),ISBLANK(K116)),"N/A","not answered/error"))) -> not answered/error
A117: IFA | B117: IFA v6 Smart | C117: AQ | D117: AQ-Smart 19.01.06 | E117: AQ 19 CHEMICAL COMPOUNDS | F117: Chemical compounds are stored in their original packaging or dedicated suitable containers, to allow label instructions to be clearly identified. | G117: Chemical compounds shall be stored in well maintained original packaging or dedicated suitable containers with readable labels. Small quantities for daily use may be put in suitable containers labeled with the chemical compound name. | I117: Major Must | M117: =IF(AND(J117<>"",ISBLANK(K117),ISBLANK(L117)),"Yes",IF(AND(K117<>"",ISBLANK(J117),ISBLANK(L117)),"No",IF(AND(L117<>"",ISBLANK(J117),ISBLANK(K117)),"N/A","not answered/error"))) -> not answered/error
A118: IFA | B118: IFA v6 Smart | C118: AQ | D118: AQ-Smart 19.01.07 | E118: AQ 19 CHEMICAL COMPOUNDS | F118: The chemical compound storage is well ventilated, able to retain spillage, and equipped with emergency facilities to deal with accidental spillage. | G118: The chemical compound storage shall be visually assessed to prove that it is well ventilated and have retaining tanks or a bund of at least 110% of the largest liquid container to ensure that there cannot be any leakage or contamination to the exterior of the store. The chemical compound storage facilities and all mixing areas shall be equipped with a container of absorbent inert material (e.g., sand), a floor brush, a dustpan, and plastic bags in a fixed location with a sign giving instructions in case of accidental spillage of concentrated chemical compounds. For diesel and other fuel oil refer to AQ 06.02.03. No “N/A.” | I118: Major Must | M118: =IF(AND(J118<>"",ISBLANK(K118),ISBLANK(L118)),"Yes",IF(AND(K118<>"",ISBLANK(J118),ISBLANK(L118)),"No",IF(AND(L118<>"",ISBLANK(J118),ISBLANK(K118)),"N/A","not answered/error"))) -> not answered/error
A119: IFA | B119: IFA v6 Smart | C119: AQ | D119: AQ-Smart 19.01.08 | E119: AQ 19 CHEMICAL COMPOUNDS | F119: Facilities and equipment are suitable for measuring and/or mixing chemical compounds to ensure safe and accurate dosage. | G119: The chemical compound measuring/mixing areas shall have suitable equipment for accurate measuring and dosing of all chemical compounds in store, including measuring cups, jars, and scales. Dosing equipment shall be identified and where relevant, shall be regularly calibrated or verified with documentary evidence and justified frequency. The equipment shall not be used for other purposes. Calibration shall be traceable to a national or international standard or method. No “N/A.” | I119: Major Must | M119: =IF(AND(J119<>"",ISBLANK(K119),ISBLANK(L119)),"Yes",IF(AND(K119<>"",ISBLANK(J119),ISBLANK(L119)),"No",IF(AND(L119<>"",ISBLANK(J119),ISBLANK(K119)),"N/A","not answered/error"))) -> not answered/error | Q119: Record date of last calibration/verification for the equipment using in the measuring and dosing of all chemical compounds.
A120: IFA | B120: IFA v6 Smart | C120: AQ | D120: AQ-Smart 19.01.09 | E120: AQ 19 CHEMICAL COMPOUNDS | F120: Suitable equipment is available to prevent and to deal with operator contamination. | G120: The chemical compound storage and measuring/mixing areas shall be visually assessed to prove they are sufficiently equipped to prevent and deal with operator contamination for all chemical compounds in store. Personal protective equipment (PPE) shall include protective gloves, eye-protectors, face masks (where required), eye wash capabilities, a source of water, a first aid kit and a clear accident emergency procedure. Procedures shall clearly warn that workers at greater risk (such as pregnant or lactating women) shall not handle hazardous substances. No “N/A.” | I120: Major Must | M120: =IF(AND(J120<>"",ISBLANK(K120),ISBLANK(L120)),"Yes",IF(AND(K120<>"",ISBLANK(J120),ISBLANK(L120)),"No",IF(AND(L120<>"",ISBLANK(J120),ISBLANK(K120)),"N/A","not answered/error"))) -> not answered/error | Q120: Brief description of equipment to deal with operator contamination. Cross checked with AQ 19.01.02
A121: IFA | B121: IFA v6 Smart | C121: AQ | D121: AQ-Smart 19.02.01 | E121: AQ 19 CHEMICAL COMPOUNDS | F121: Empty chemical compound containers have records in place for reuse, recycling, and/or disposal. Reuse is possible only when risk-assessed by a competent person. | G121: There shall be evidence that empty chemical compound containers are not reused in any form unless risk-assessed as safe by a competent person. There are records that chemical compound containers have been disposed of by a legally licensed chemical compound waste subcontractor or returned to the supplying company for recycling. No “N/A.” | I121: Major Must | M121: =IF(AND(J121<>"",ISBLANK(K121),ISBLANK(L121)),"Yes",IF(AND(K121<>"",ISBLANK(J121),ISBLANK(L121)),"No",IF(AND(L121<>"",ISBLANK(J121),ISBLANK(K121)),"N/A","not answered/error"))) -> not answered/error | Q121: Name of the collection system (if exists): Date of last record of disposal of chemical compound waste. Subcontractors for disposal of empty chemical containers: yes/no.
A122: IFA | B122: IFA v6 Smart | C122: AQ | D122: AQ-Smart 19.02.02 | E122: AQ 19 CHEMICAL COMPOUNDS | F122: The storage and disposal of empty containers and unused chemical compounds is carried out in such a way as to avoid spills or rinses that may expose products, humans, and/or animals. | G122: The system used for storage and disposal of empty chemical compound containers and unused chemical compounds shall ensure that products, persons, or animals cannot come into contact with the empty containers or chemical compounds and that spills or rinses are avoided. There shall be records that document that chemical compounds have been disposed of by officially authorized channels. No “N/A.” | I122: Major Must | M122: =IF(AND(J122<>"",ISBLANK(K122),ISBLANK(L122)),"Yes",IF(AND(K122<>"",ISBLANK(J122),ISBLANK(L122)),"No",IF(AND(L122<>"",ISBLANK(J122),ISBLANK(K122)),"N/A","not answered/error"))) -> not answered/error | Q122: Name of the collection system (if exists): Date of last record of disposal of unused chemical compounds. Subcontractors for disposal of unused chemical compounds: yes/no.
A123: IFA | B123: IFA v6 Smart | C123: AQ | D123: AQ-Smart 19.03.01 | E123: AQ 19 CHEMICAL COMPOUNDS | F123: Chemical compounds are transported according to documented procedures. | G123: A documented procedure for chemical compounds transport shall be available and consider food safety, health, safety, and environmental risks. | I123: Minor Must | M123: =IF(AND(J123<>"",ISBLANK(K123),ISBLANK(L123)),"Yes",IF(AND(K123<>"",ISBLANK(J123),ISBLANK(L123)),"No",IF(AND(L123<>"",ISBLANK(J123),ISBLANK(K123)),"N/A","not answered/error"))) -> not answered/error
A124: IFA | B124: IFA v6 Smart | C124: AQ | D124: AQ-Smart 20.01.01 | E124: AQ 20 FARMED AQUATIC SPECIES WELFARE, MANAGEMENT, AND HUSBANDRY (at all points of the production chain) | F124: Farmed aquatic species are traceable to the previous farm(s) and back to their origins, including identification of corresponding batch(es) of seedlings and parents. | G124: Farmed aquatic species shall be traceable to the previous farm(s) and back to their origins, including identification of corresponding batch(es) of seedlings and parents. Traceability records shall be on site. No “N/A.” | I124: Major Must | M124: =IF(AND(J124<>"",ISBLANK(K124),ISBLANK(L124)),"Yes",IF(AND(K124<>"",ISBLANK(J124),ISBLANK(L124)),"No",IF(AND(L124<>"",ISBLANK(J124),ISBLANK(K124)),"N/A","not answered/error"))) -> not answered/error | Q124: TRACEABILITY PROCEDURE XXXX - Date: DD/MM/YY; Document identification of batch traceability example taken at the time of the audit: Tracing Backward. Product Checked: XXXX; Delivery Date: DD/MM/YY - Lot number in the Label: XXXX; GGN : XXX; Customer: XXXX; Documet of Trasport: XXXX; Harvest Date: DD/MM/YY - Lot/Batch Number: XXXX - Traced Back to the TANK/CAGE: XXXX Movements:XXXX Sowing date:XXXX; Supplier arrival documentation (e.g., purchase, transport, health certificate, parents, seedling/stock origin) XXXXX; Product Handling: The traceability system also encompasses product handling. For instance, if the product undergo post-harvest processing at an on-site facility, the traceability records extend to cover this aspect. EXAMPLE : Date: DD/MM/YY Verification of Traceability System: Annual Verification: The Producer conducts an annual verification of its traceability system. Last test: DD/MM/YY- Product : XXXX and/or Recall/Withdraw Mock exercise: DD/MM/YY - Product: XXX
A125: IFA | B125: IFA v6 Smart | C125: AQ | D125: AQ-Smart 20.01.02 | E125: AQ 20 FARMED AQUATIC SPECIES WELFARE, MANAGEMENT, AND HUSBANDRY (at all points of the production chain) | F125: Farmed aquatic species movements, at any life stage within, to, and from the farm, are recorded and traceable. | G125: Traceability records shall be on site. Records of all stock movements for all stages in the aquatic specie(s)’s life cycle shall include, where applicable: seedling/stock origin, species, numbers, biomass, and production unit ID. | I125: Major Must | M125: =IF(AND(J125<>"",ISBLANK(K125),ISBLANK(L125)),"Yes",IF(AND(K125<>"",ISBLANK(J125),ISBLANK(L125)),"No",IF(AND(L125<>"",ISBLANK(J125),ISBLANK(K125)),"N/A","not answered/error"))) -> not answered/error | Q125: Document identification of movement example taken at the time of the audit: name: code: revision: date: seedling/stock origin: species: biomass: production ID:
A126: IFA | B126: IFA v6 Smart | C126: AQ | D126: AQ-Smart 20.01.03 | E126: AQ 20 FARMED AQUATIC SPECIES WELFARE, MANAGEMENT, AND HUSBANDRY (at all points of the production chain) | F126: Farmed aquatic species are identified (on a batch level) to specific batch(es) or input throughout the growing period. | G126: At each stage of the growth cycle, it shall be possible to identify the composition of a batch from its inputs. No “N/A.” | I126: Major Must | M126: =IF(AND(J126<>"",ISBLANK(K126),ISBLANK(L126)),"Yes",IF(AND(K126<>"",ISBLANK(J126),ISBLANK(L126)),"No",IF(AND(L126<>"",ISBLANK(J126),ISBLANK(K126)),"N/A","not answered/error"))) -> not answered/error | Q126: Document identification of batch composition example: XXXXX
A127: IFA | B127: IFA v6 Smart | C127: AQ | D127: AQ-Smart 20.01.04 | E127: AQ 20 FARMED AQUATIC SPECIES WELFARE, MANAGEMENT, AND HUSBANDRY (at all points of the production chain) | F127: Farmed brood stock is purchased from a source with GLOBALG.A.P. certification for the Integrated Farm Assurance (IFA) standard for aquaculture. | G127: The records of purchase and certificates should be available for the certification body (CB) audit. Management should be able to demonstrate awareness at interview. | I127: Recommendation | M127: =IF(AND(J127<>"",ISBLANK(K127),ISBLANK(L127)),"Yes",IF(AND(K127<>"",ISBLANK(J127),ISBLANK(L127)),"No",IF(AND(L127<>"",ISBLANK(J127),ISBLANK(K127)),"N/A","not answered/error"))) -> not answered/error | Q127: Brood stock included in the scope of certification: yes/no?
A128: IFA | B128: IFA v6 Smart | C128: AQ | D128: AQ-Smart 20.01.05 | E128: AQ 20 FARMED AQUATIC SPECIES WELFARE, MANAGEMENT, AND HUSBANDRY (at all points of the production chain) | F128: Seedlings originate from a supplier (internal or external) with GLOBALG.A.P. certification for the Integrated Farm Assurance (IFA) standard for aquaculture. | G128: The records and certificates shall be available for the certification body (CB) audit. Management shall be able to demonstrate awareness at interview. - Certification audit: For initial compliance purposes, it is required that seedlings suppliers are registered with a GLOBALG.A.P. Number (GGN) in the GLOBALG.A.P. IT systems (as “GLOBALG.A.P. aquaculture seedlings (ova/juvenile)”) at the time of the producer’s initial CB audit. The supplier shall be able to show evidence of a self-assessment and provide a letter of commitment to certification by next CB audit. - Subsequent audit (second CB audit): Suppliers shall have GLOBALG.A.P. certification or certification to a GLOBALG.A.P. benchmarked scheme. Ongoing compliance at subsequent audits of the seedling supplier(s) (whether internal or external suppliers), is required. - After this first year, any additional seedling suppliers that start supplying the farm with GLOBALG.A.P. certification, shall be registered in the GLOBALG.A.P. IT systems from the moment seedlings are purchased and shall demonstrate their GLOBALG.A.P. certification status at their first CB audit after they started supplying. No “N/A.” | I128: Major Must | M128: =IF(AND(J128<>"",ISBLANK(K128),ISBLANK(L128)),"Yes",IF(AND(K128<>"",ISBLANK(J128),ISBLANK(L128)),"No",IF(AND(L128<>"",ISBLANK(J128),ISBLANK(K128)),"N/A","not answered/error"))) -> not answered/error | Q128: Initial audit: seedlings certified: yes/no? If yes, corresponding GGNs shall be indicated in the audit report. Subsequent audits: GGNs shall be indicated in the audit report. In both cases above, the CB need to validate the respective GGNs.
A129: IFA | B129: IFA v6 Smart | C129: AQ | D129: AQ-Smart 20.01.06 | E129: AQ 20 FARMED AQUATIC SPECIES WELFARE, MANAGEMENT, AND HUSBANDRY (at all points of the production chain) | F129: Following certification, all stocked farmed aquatic species have spent their entire life on GLOBALG.A.P. registered farm(s). | G129: Movement traceability records shall be in place to prove that all stocked farmed aquatic species since certification come only from GLOBALG.A.P. registered farms. | I129: Major Must | M129: =IF(AND(J129<>"",ISBLANK(K129),ISBLANK(L129)),"Yes",IF(AND(K129<>"",ISBLANK(J129),ISBLANK(L129)),"No",IF(AND(L129<>"",ISBLANK(J129),ISBLANK(K129)),"N/A","not answered/error"))) -> not answered/error | Q129: Interview with responsible person shows evidence that movement traceability records are understood.
A130: IFA | B130: IFA v6 Smart | C130: AQ | D130: AQ-Smart 20.02.01 | E130: AQ 20 FARMED AQUATIC SPECIES WELFARE, MANAGEMENT, AND HUSBANDRY (at all points of the production chain) | F130: An aquaculture health plan (AHP) is available, updated during the last 12 months, for the last production cycle, or whenever new medicines or treatments not previously used have been added. | G130: An AHP shall be available on the site. A certified veterinarian/aquatic animal health professional recognized by a competent authority shall approve the AHP. Name, affiliation, and dated signature shall be included in the AHP. A certified veterinarian/aquatic animal health professional is the professional responsible for health management on the farm who has the legal authority to diagnose disease and prescribe medication. This definition applies to all references to a veterinarian throughout the standard documents. The AHP shall be updated either: a) Annually b) For each production cycle, if farmed aquatic species are on the farm for a period shorter than one year c) Whenever any of the content of the AHP requires updating (e.g., inclusion of new medicines or treatments) The plan shall include but is not restricted to the following: 1. Name and location of farm(s) 2. Potential diseases, including corresponding preventive measures of disease spread and disease mitigation 3. Vaccination protocols, which shall include available vaccines suitable for preventing or reducing possible diseases which could occur in this region, where applicable. If effective vaccines are available for a recurring disease, vaccination shall be preferred over therapeutic treatments. All fish shall be anesthetized prior to vaccination by injection, unless there are well justified health and welfare reasons not to do so. Sedation should be used when vaccinating by dip or bath if there is a risk of injury during handling. 4. Quarantine procedures 5. Medicines and treatments that may be used on the farm, including medicine name, active substance, indication, supplier, administration method, dosage, and preharvest withdrawal period 6. Preharvest withdrawal period, beginning when medicated feed is flushed from the farm feeding system; use of flushed feeds (feed intended to clear residues from the feed system) 7. Parasite records and controls, including frequency 8. Biosecurity procedures 9. Screening program for relevant pathogens 10. Risk assessment of medicinal residues in relation to food safety issues and potential impact on wild stocks around the farm 11. Stunning and killing procedures, including those for brood stock 12. Action plan for harvestable farmed aquatic species if the maximum residue limit (MRL) in the country of production and/or destination has been exceeded or is likely to be exceeded 13. Frequency and methods of culling, removal of sick and disposal of dead animals 14. Frequency and methods of mortality inspection 15. Frequency of monitoring of sensitivity/resistance and rotation of medicines to avoid antimicrobial resistance (AMR), where applicable 16. Recording of mortality and its causes, which shall be done daily or as often as possible. Where a disease outbreak is suspected or mortalities are higher than expected, the veterinarian/aquatic animal health professional and relevant government official shall be notified. 17. Internal procedure for disease breakout notification, including who will be notified 18. Animal health treatments: Antibiotics shall be used if and only if specific diseases are diagnosed and there is no alternative and farmed aquatic species welfare and health may be compromised. 18.a) Critically important antimicrobials as per the World Health Organization (WHO, www.who.int) recommendations shall be used if and only if it is the only last resort. Critical important antimicrobials (highest priority and high priority) listed for human medicine can be used only in exceptional circumstances under the judgement, prescription, and supervision of a veterinarian/aquatic animal health professional and if microbial sensitivity results (historic antibiogram) demonstrate that the selected antimicrobial is the only efficient treatment option. The veterinarian/aquatic animal health professional shall give justification in writing for each occasion of this use. If there is such use, there shall be evidence of communication from the producer’s certified veterinarian/aquatic animal health professional instructing the feed suppliers to mix prescribed antimicrobials into compound feed. It is the responsibility of the farmer to inform an external prescribing veterinarian or aquatic animal health professional of this requirement. 18.b) Consideration of the World Organization for Animal Health (WOAH, www.woah.org) recommendations on the “WOAH List of Antimicrobial Agents of Veterinary Importance”: “Among the VCIA – Veterinary Critically Important Antimicrobial Agents in the WOAH List, some are considered to be critically important both for human and animal health; this is currently the case for Fluoroquinolones and for the third and fourth generation of Cephalosporins. Colistin has been moved in 2016 to the WHO category of Highest Priority Critically Important Antimicrobials. Therefore, these two classes and Colistin should be used according to the following recommendations: - Not to be used as preventive treatment; - Not to be used as a first line treatment unless justified, when used as a second line treatment, it should ideally be based on the results of bacteriological tests; and - Extra-label/off-label use should be limited and reserved for instances where no alternatives are available. Such use should be in agreement with the national legislation in force;” 19. Any trials or testing of nonlicensed medical treatments 20. Fallowing periods and procedure instructions, where applicable 21. Coordinated disease responses and preventive measures with neighboring farmers 22. Medicines and treatments that are not allowed to be used, which shall include those compounds that are banned under the United Nations Food and Agriculture Organization (FAO)/WHO Codex Alimentarius: nitrofurans (as well as its derivates), triarylmethane dyes (including, but not limited to malachite green, crystal violet, and brilliant green), stilbenes (including, but not limited to stilbene, dienestrol, diethylstilbestrol, hexestrol), chloramphenicol, nitroimidazoles (including, but not limited to dimetridazole, ipronidazole, metronidazole) or ß-agonists (including, but not limited to clenbuterol) 23. Where applicable, records of routine assigned veterinarian/aquatic animal health professional visits No “N/A.” | I130: Major Must | M130: =IF(AND(J130<>"",ISBLANK(K130),ISBLANK(L130)),"Yes",IF(AND(K130<>"",ISBLANK(J130),ISBLANK(L130)),"No",IF(AND(L130<>"",ISBLANK(J130),ISBLANK(K130)),"N/A","not answered/error"))) -> not answered/error | Q130: Qualifications and requirements of the person that approved and signed the AHP have been verified (no personal data should be recorded). Document identification name: code: revision: date: Content verification of the AHP: + Updated accordingly. + Items number applicable to the operation. + Items number not applicable to the operation.
A131: IFA | B131: IFA v6 Smart | C131: AQ | D131: AQ-Smart 20.02.02 | E131: AQ 20 FARMED AQUATIC SPECIES WELFARE, MANAGEMENT, AND HUSBANDRY (at all points of the production chain) | F131: Equipment is designed and fit for the purpose of avoiding physical damage and ensuring minimal stress to the farmed aquatic species. | G131: Pumps, surfaces, and equipment that come into contact with farmed aquatic species, including vaccination facilities, shall be suitably designed and operated to avoid physical damage and to ensure minimal stress to the farmed aquatic species. | I131: Major Must | M131: =IF(AND(J131<>"",ISBLANK(K131),ISBLANK(L131)),"Yes",IF(AND(K131<>"",ISBLANK(J131),ISBLANK(L131)),"No",IF(AND(L131<>"",ISBLANK(J131),ISBLANK(K131)),"N/A","not answered/error"))) -> not answered/error
...

Sheet Audit Result
A3: GGN*: | E3: IFA v6 Smart Aquaculture
A4: Audit Date* | E4: Audited Company*:
A5: Principle | B5: Level | C5: Original Answer | D5: Justification | E5: Due date | F5: Corrective actions* | G5: Closed? (x)* | H5: Status | I5: Closed by* | J5: Closed on* | K5: Comments*
A6: ='CL - IFA v6 Smart - AQ'!D10 -> AQ-Smart 01.01.01 | B6: ='CL - IFA v6 Smart - AQ'!I10 -> Major Must | C6: =IF('CL - IFA v6 Smart - AQ'!M10 = 0,"",'CL - IFA v6 Smart - AQ'!M10) -> not answered/error | D6: =IF('CL - IFA v6 Smart - AQ'!Q10 = 0, "",'CL - IFA v6 Smart - AQ'!Q10) -> Confirmation that a map is available and that it clearly identifies all sites. If physical signs are in place, this shall be recorded. | E6: =IF('CL - IFA v6 Smart - AQ'!R10 = 0,"",'CL - IFA v6 Smart - AQ'!R10) | H6: =IF('Audit Result'!C6 = "No", IF('Audit Result'!G6 = "x", "Closed", "Open"), "")
A7: ='CL - IFA v6 Smart - AQ'!D11 -> AQ-Smart 01.01.02 | B7: ='CL - IFA v6 Smart - AQ'!I11 -> Major Must | C7: =IF('CL - IFA v6 Smart - AQ'!M11 = 0,"",'CL - IFA v6 Smart - AQ'!M11) -> not answered/error | D7: =IF('CL - IFA v6 Smart - AQ'!Q11 = 0, "",'CL - IFA v6 Smart - AQ'!Q11) -> Identification of the site and the period where all history of activities were revised. | E7: =IF('CL - IFA v6 Smart - AQ'!R11 = 0,"",'CL - IFA v6 Smart - AQ'!R11) | H7: =IF('Audit Result'!C7 = "No", IF('Audit Result'!G7 = "x", "Closed", "Open"), "")
A8: ='CL - IFA v6 Smart - AQ'!D12 -> AQ-Smart 01.02.01 | B8: ='CL - IFA v6 Smart - AQ'!I12 -> Major Must | C8: =IF('CL - IFA v6 Smart - AQ'!M12 = 0,"",'CL - IFA v6 Smart - AQ'!M12) -> not answered/error | D8: =IF('CL - IFA v6 Smart - AQ'!Q12 = 0, "",'CL - IFA v6 Smart - AQ'!Q12) -> A documented risk assessment is available with a list A list of all activities potentially affecting the aquaculture farm: potential physical, chemical (including allergens), and biological hazards. Document identification name: code: revision: date: | E8: =IF('CL - IFA v6 Smart - AQ'!R12 = 0,"",'CL - IFA v6 Smart - AQ'!R12) | H8: =IF('Audit Result'!C8 = "No", IF('Audit Result'!G8 = "x", "Closed", "Open"), "")
A9: ='CL - IFA v6 Smart - AQ'!D13 -> AQ-Smart 01.02.02 | B9: ='CL - IFA v6 Smart - AQ'!I13 -> Major Must | C9: =IF('CL - IFA v6 Smart - AQ'!M13 = 0,"",'CL - IFA v6 Smart - AQ'!M13) -> not answered/error | D9: =IF('CL - IFA v6 Smart - AQ'!Q13 = 0, "",'CL - IFA v6 Smart - AQ'!Q13) -> A management pla address the risks identified in AQ 01.02.01. Document identification name: code: revision: date: | E9: =IF('CL - IFA v6 Smart - AQ'!R13 = 0,"",'CL - IFA v6 Smart - AQ'!R13) | H9: =IF('Audit Result'!C9 = "No", IF('Audit Result'!G9 = "x", "Closed", "Open"), "")
A10: ='CL - IFA v6 Smart - AQ'!D14 -> AQ-Smart 01.02.03 | B10: ='CL - IFA v6 Smart - AQ'!I14 -> Major Must | C10: =IF('CL - IFA v6 Smart - AQ'!M14 = 0,"",'CL - IFA v6 Smart - AQ'!M14) -> not answered/error | D10: =IF('CL - IFA v6 Smart - AQ'!Q14 = 0, "",'CL - IFA v6 Smart - AQ'!Q14) | E10: =IF('CL - IFA v6 Smart - AQ'!R14 = 0,"",'CL - IFA v6 Smart - AQ'!R14) | H10: =IF('Audit Result'!C10 = "No", IF('Audit Result'!G10 = "x", "Closed", "Open"), "")
A11: ='CL - IFA v6 Smart - AQ'!D15 -> AQ-Smart 01.03.01 | B11: ='CL - IFA v6 Smart - AQ'!I15 -> Major Must | C11: =IF('CL - IFA v6 Smart - AQ'!M15 = 0,"",'CL - IFA v6 Smart - AQ'!M15) -> not answered/error | D11: =IF('CL - IFA v6 Smart - AQ'!Q15 = 0, "",'CL - IFA v6 Smart - AQ'!Q15) | E11: =IF('CL - IFA v6 Smart - AQ'!R15 = 0,"",'CL - IFA v6 Smart - AQ'!R15) | H11: =IF('Audit Result'!C11 = "No", IF('Audit Result'!G11 = "x", "Closed", "Open"), "")
A12: ='CL - IFA v6 Smart - AQ'!D16 -> AQ-Smart 01.03.02 | B12: ='CL - IFA v6 Smart - AQ'!I16 -> Major Must | C12: =IF('CL - IFA v6 Smart - AQ'!M16 = 0,"",'CL - IFA v6 Smart - AQ'!M16) -> not answered/error | D12: =IF('CL - IFA v6 Smart - AQ'!Q16 = 0, "",'CL - IFA v6 Smart - AQ'!Q16) -> Document identification name/type of licence: code: revision: date: institution that issue the license: Date of validity of the license/permit. | E12: =IF('CL - IFA v6 Smart - AQ'!R16 = 0,"",'CL - IFA v6 Smart - AQ'!R16) | H12: =IF('Audit Result'!C12 = "No", IF('Audit Result'!G12 = "x", "Closed", "Open"), "")
A13: ='CL - IFA v6 Smart - AQ'!D17 -> AQ-Smart 02.01 | B13: ='CL - IFA v6 Smart - AQ'!I17 -> Major Must | C13: =IF('CL - IFA v6 Smart - AQ'!M17 = 0,"",'CL - IFA v6 Smart - AQ'!M17) -> not answered/error | D13: =IF('CL - IFA v6 Smart - AQ'!Q17 = 0, "",'CL - IFA v6 Smart - AQ'!Q17) -> all records verified show as a minimum three months of recording. Example: XXXXXXXXXXX For consecutive audits, report: "Consecutive audit." | E13: =IF('CL - IFA v6 Smart - AQ'!R17 = 0,"",'CL - IFA v6 Smart - AQ'!R17) | H13: =IF('Audit Result'!C13 = "No", IF('Audit Result'!G13 = "x", "Closed", "Open"), "")
A14: ='CL - IFA v6 Smart - AQ'!D18 -> AQ-Smart 02.02 | B14: ='CL - IFA v6 Smart - AQ'!I18 -> Major Must | C14: =IF('CL - IFA v6 Smart - AQ'!M18 = 0,"",'CL - IFA v6 Smart - AQ'!M18) -> not answered/error | D14: =IF('CL - IFA v6 Smart - AQ'!Q18 = 0, "",'CL - IFA v6 Smart - AQ'!Q18) -> Document identification name: code: revision: date: | E14: =IF('CL - IFA v6 Smart - AQ'!R18 = 0,"",'CL - IFA v6 Smart - AQ'!R18) | H14: =IF('Audit Result'!C14 = "No", IF('Audit Result'!G14 = "x", "Closed", "Open"), "")
A15: ='CL - IFA v6 Smart - AQ'!D19 -> AQ-Smart 02.03 | B15: ='CL - IFA v6 Smart - AQ'!I19 -> Major Must | C15: =IF('CL - IFA v6 Smart - AQ'!M19 = 0,"",'CL - IFA v6 Smart - AQ'!M19) -> not answered/error | D15: =IF('CL - IFA v6 Smart - AQ'!Q19 = 0, "",'CL - IFA v6 Smart - AQ'!Q19) -> Document identification name: code: revision: date: | E15: =IF('CL - IFA v6 Smart - AQ'!R19 = 0,"",'CL - IFA v6 Smart - AQ'!R19) | H15: =IF('Audit Result'!C15 = "No", IF('Audit Result'!G15 = "x", "Closed", "Open"), "")
A16: ='CL - IFA v6 Smart - AQ'!D20 -> AQ-Smart 02.04 | B16: ='CL - IFA v6 Smart - AQ'!I20 -> Major Must | C16: =IF('CL - IFA v6 Smart - AQ'!M20 = 0,"",'CL - IFA v6 Smart - AQ'!M20) -> not answered/error | D16: =IF('CL - IFA v6 Smart - AQ'!Q20 = 0, "",'CL - IFA v6 Smart - AQ'!Q20) -> Geographical coordinates of all sites: | E16: =IF('CL - IFA v6 Smart - AQ'!R20 = 0,"",'CL - IFA v6 Smart - AQ'!R20) | H16: =IF('Audit Result'!C16 = "No", IF('Audit Result'!G16 = "x", "Closed", "Open"), "")
A17: ='CL - IFA v6 Smart - AQ'!D21 -> AQ-Smart 02.05 | B17: ='CL - IFA v6 Smart - AQ'!I21 -> Major Must | C17: =IF('CL - IFA v6 Smart - AQ'!M21 = 0,"",'CL - IFA v6 Smart - AQ'!M21) -> not answered/error | D17: =IF('CL - IFA v6 Smart - AQ'!Q21 = 0, "",'CL - IFA v6 Smart - AQ'!Q21) -> examples of records verified: -XXXXXXX -XXXXXXX -XXXXXXX Describe where the records are kept/stored. | E17: =IF('CL - IFA v6 Smart - AQ'!R21 = 0,"",'CL - IFA v6 Smart - AQ'!R21) | H17: =IF('Audit Result'!C17 = "No", IF('Audit Result'!G17 = "x", "Closed", "Open"), "")
... A262: ='CL - IFA v6 Smart - AQ'!D266 -> AQ-Smart 28.06.02 | B262: ='CL - IFA v6 Smart - AQ'!I266 -> Major Must | C262: =IF('CL - IFA v6 Smart - AQ'!M266 = 0,"",'CL - IFA v6 Smart - AQ'!M266) -> not answered/error | D262: =IF('CL - IFA v6 Smart - AQ'!Q266 = 0, "",'CL - IFA v6 Smart - AQ'!Q266) | E262: =IF('CL - IFA v6 Smart - AQ'!R266 = 0,"",'CL - IFA v6 Smart - AQ'!R266) | H262: =IF('Audit Result'!C262 = "No", IF('Audit Result'!G262 = "x", "Closed", "Open"), "")
A273: Summary
A274: Original calculation after the end of Audit
A275: Type | B275: Total Amount Checklist | C275: Yes | D275: No | E275: N/A | F275: Not answered | G275: NC Closed | H275: % Compliance
A276: Major | B276: =COUNTIF('CL - IFA v6 Smart - AQ'!I10:'CL - IFA v6 Smart - AQ'!I266, "Major Must") -> 230 | C276: =COUNTIFS('CL - IFA v6 Smart - AQ'!I10:'CL - IFA v6 Smart - AQ'!I266, "Major Must",'CL - IFA v6 Smart - AQ'!M10:'CL - IFA v6 Smart - AQ'!M266, "Yes") -> 0 | D276: =COUNTIFS('CL - IFA v6 Smart - AQ'!I10:'CL - IFA v6 Smart - AQ'!I266, "Major Must",'CL - IFA v6 Smart - AQ'!M10:'CL - IFA v6 Smart - AQ'!M266, "No") -> 0 | E276: =COUNTIFS('CL - IFA v6 Smart - AQ'!I10:'CL - IFA v6 Smart - AQ'!I266, "Major Must",'CL - IFA v6 Smart - AQ'!M10:'CL - IFA v6 Smart - AQ'!M266, "N/A") -> 0 | F276: =B276-(C276+D276+E276) -> 230 | H276: =IFERROR(IF((C276+G276)/(B276-E276) = 0, " - ", (C276+G276)/(B276-E276))," - ") -> -
A277: Minor | B277: =COUNTIF('CL - IFA v6 Smart - AQ'!I10:'CL - IFA v6 Smart - AQ'!I266, "Minor Must") -> 22 | C277: =COUNTIFS('CL - IFA v6 Smart - AQ'!I10:'CL - IFA v6 Smart - AQ'!I266, "Minor Must",'CL - IFA v6 Smart - AQ'!M10:'CL - IFA v6 Smart - AQ'!M266, "Yes") -> 0 | D277: =COUNTIFS('CL - IFA v6 Smart - AQ'!I10:'CL - IFA v6 Smart - AQ'!I266, "Minor Must",'CL - IFA v6 Smart - AQ'!M10:'CL - IFA v6 Smart - AQ'!M266, "No") -> 0 | E277: =COUNTIFS('CL - IFA v6 Smart - AQ'!I10:'CL - IFA v6 Smart - AQ'!I266, "Minor Must",'CL - IFA v6 Smart - AQ'!M10:'CL - IFA v6 Smart - AQ'!M266, "N/A") -> 0 | F277: =B277-(C277+D277+E277) -> 22 | H277: =IFERROR(IF((C277+G277)/(B277-E277) = 0, " - ", (C277+G277)/(B277-E277))," - ") -> -
A278: Recommendation | B278: =COUNTIF('CL - IFA v6 Smart - AQ'!I10:'CL - IFA v6 Smart - AQ'!I266, "Recommendation") -> 5 | C278: =COUNTIFS('CL - IFA v6 Smart - AQ'!I10:'CL - IFA v6 Smart - AQ'!I266, "Recommendation",'CL - IFA v6 Smart - AQ'!M10:'CL - IFA v6 Smart - AQ'!M266, "Yes") -> 0 | D278: =COUNTIFS('CL - IFA v6 Smart - AQ'!I10:'CL - IFA v6 Smart - AQ'!I266, "Recommendation",'CL - IFA v6 Smart - AQ'!M10:'CL - IFA v6 Smart - AQ'!M266, "No") -> 0 | E278: =COUNTIFS('CL - IFA v6 Smart - AQ'!I10:'CL - IFA v6 Smart - AQ'!I266, "Recommendation",'CL - IFA v6 Smart - AQ'!M10:'CL - IFA v6 Smart - AQ'!M266, "N/A") -> 0 | F278: =B278-(C278+D278+E278) -> 5 | H278: =IFERROR(IF((C278+G278)/(B278-E278) = 0, " - ", (C278+G278)/(B278-E278))," - ") -> -
A280: Revised calculation after Non-Compliance points are closed
A281: Type | B281: Total Amount Checklist | C281: Yes | D281: No | E281: N/A | F281: Not answered | G281: NC Closed | H281: % Compliance
A282: Major | B282: =COUNTIF('CL - IFA v6 Smart - AQ'!I10:'CL - IFA v6 Smart - AQ'!I266, "Major Must") -> 230 | C282: =COUNTIFS('CL - IFA v6 Smart - AQ'!I10:'CL - IFA v6 Smart - AQ'!I266, "Major Must",'CL - IFA v6 Smart - AQ'!M10:'CL - IFA v6 Smart - AQ'!M266, "Yes") -> 0 | D282: =COUNTIFS('CL - IFA v6 Smart - AQ'!I10:'CL - IFA v6 Smart - AQ'!I266, "Major Must",'CL - IFA v6 Smart - AQ'!M10:'CL - IFA v6 Smart - AQ'!M266, "No") -> 0 | E282: =COUNTIFS('CL - IFA v6 Smart - AQ'!I10:'CL - IFA v6 Smart - AQ'!I266, "Major Must",'CL - IFA v6 Smart - AQ'!M10:'CL - IFA v6 Smart - AQ'!M266, "N/A") -> 0 | F282: =B282-(C282+D282+E282) -> 230 | G282: =COUNTIFS(B6:B262,"Major Must",H6:H262, "Closed") -> 0 | H282: =IFERROR(IF((C282+G282)/(B282-E282) = 0, " - ", (C282+G282)/(B282-E282))," - ") -> -
A283: Minor | B283: =COUNTIF('CL - IFA v6 Smart - AQ'!I10:'CL - IFA v6 Smart - AQ'!I266, "Minor Must") -> 22 | C283: =COUNTIFS('CL - IFA v6 Smart - AQ'!I10:'CL - IFA v6 Smart - AQ'!I266, "Minor Must",'CL - IFA v6 Smart - AQ'!M10:'CL - IFA v6 Smart - AQ'!M266, "Yes") -> 0 | D283: =COUNTIFS('CL - IFA v6 Smart - AQ'!I10:'CL - IFA v6 Smart - AQ'!I266, "Minor Must",'CL - IFA v6 Smart - AQ'!M10:'CL - IFA v6 Smart - AQ'!M266, "No") -> 0 | E283: =COUNTIFS('CL - IFA v6 Smart - AQ'!I10:'CL - IFA v6 Smart - AQ'!I266, "Minor Must",'CL - IFA v6 Smart - AQ'!M10:'CL - IFA v6 Smart - AQ'!M266, "N/A") -> 0 | F283: =B283-(C283+D283+E283) -> 22 | G283: =COUNTIFS(B6:B262,"Minor Must",H6:H262, "Closed") -> 0 | H283: =IFERROR(IF((C283+G283)/(B283-E283) = 0, " - ", (C283+G283)/(B283-E283))," - ") -> -
A284: Recommendation | B284: =COUNTIF('CL - IFA v6 Smart - AQ'!I10:'CL - IFA v6 Smart - AQ'!I266, "Recommendation") -> 5 | C284: =COUNTIFS('CL - IFA v6 Smart - AQ'!I10:'CL - IFA v6 Smart - AQ'!I266, "Recommendation",'CL - IFA v6 Smart - AQ'!M10:'CL - IFA v6 Smart - AQ'!M266, "Yes") -> 0 | D284: =COUNTIFS('CL - IFA v6 Smart - AQ'!I10:'CL - IFA v6 Smart - AQ'!I266, "Recommendation",'CL - IFA v6 Smart - AQ'!M10:'CL - IFA v6 Smart - AQ'!M266, "No") -> 0 | E284: =COUNTIFS('CL - IFA v6 Smart - AQ'!I10:'CL - IFA v6 Smart - AQ'!I266, "Recommendation",'CL - IFA v6 Smart - AQ'!M10:'CL - IFA v6 Smart - AQ'!M266, "N/A") -> 0 | F284: =B284-(C284+D284+E284) -> 5 | G284: =COUNTIFS(B6:B262,"Recommendation",H6:H262, "Closed") -> 0 | H284: =IFERROR(IF((C284+G284)/(B284-E284) = 0, " - ", (C284+G284)/(B284-E284))," - ") -> -

Sheet IFA Inspection Guideline

Sheet Info _ Workers welfare P&Cs
A1: LIST OF CRITERIA RELATED TO WORKERS SAFETY, WORKERS HEALTH AND WORKERS WELLBEING in IFA FO Smart | E1: LIST OF CRITERIA RELATED TO WORKERS SAFETY, WORKERS HEALTH AND WORKERS WELLBEING in IFA AQ GFS/SMART | I1: LIST OF CRITERIA RELATED TO WORKERS SAFETY, WORKERS HEALTH AND WORKERS WELLBEING in IFA v6 FV Smart and GFS
A3: Principle Number | B3: Topic | C3: Level | E3: Principle Number | F3: Topic | G3: Level | I3: Principle Number | J3: Topic | K3: Level
A4: FO 01.04.01 | B4: Records training kept | C4: minor | E4: AQ 04.03.01 | F4: Accident procedure | G4: minor | I4: FV-SMART & GFS 03.01 | J4: Role WHS representative | K4: minor (Major in GFS)
A5: FO 07.09.01 | B5: Equipment fit for use | C5: minor | E5: AQ 04.03.03 | F5: Safety Advice to workers | G5: minor | I5: FV-SMART & GFS 20.02.02 | J5: Safety Advice to workers | K5: minor
A6: FO 13.06 | B6: Toilets and washing facilities | C6: minor | E6: AQ 04.03.04 | F6: First aid kits available | G6: minor | I6: FV-SMART & GFS 20.02.03 | J6: First aid kits available | K6: minor
A7: FO 12.01.02 | B7: WHS procedures | C7: minor | E7: AQ 04.03.05 | F7: Person trained First Aid | G7: minor | I7: FV-SMART & GFS 20.02.04 | J7: Person trained First Aid | K7: minor
A8: FO 12.01.03 | B8: Training WHS | C8: minor | E8: AQ 04.05.04 | F8: Transportation safe | G8: minor | I8: FV-SMART & GFS 20.03.03 | J8: Equipment used by workers | K8: minor
A9: FO 12.02.01 | B9: Safety Advice to workers | C9: minor | E9: AQ 19.03.01 | F9: PPP transported safely | G9: minor | I9: FV-SMART & GFS 20.03.04 | J9: Changing facilities available | K9: minor
A10: FO 12.02.02 | B10: First aid kits available | C10: minor | I10: FV-SMART & GFS 20.04.01 | J10: Comm WHS worker/management | K10: minor
A11: FO 12.02.03 | B11: Person trained First Aid | C11: minor | I11: FV-SMART & GFS 20.04.04 | J11: Transportation safe | K11: minor
A12: FO 12.03.03 | B12: Equipment used by workers | C12: minor | I12: FV-SMART & GFS 25.06 | J12: Water correctly disposed | K12: minor
A13: FO 12.03.04 | B13: Changing facilities available | C13: minor | I13: FV-SMART & GFS 29.01.06 | J13: Name applicators | K13: minor
A14: FO 12.03.05 | B14: Comm WHS worker/management | C14: minor | I14: FV-SMART & GFS 32.04.03 | J14: Containers kept safely | K14: minor
A15: FO 13.05 | B15: Transportation safe | C15: minor | I15: FV-SMART & GFS 32.04.04 | J15: Containers disposed correctly | K15: minor
A16: FO 09.06 | B16: Water correctly disposed | C16: minor | I16: FV-SMART & GFS 32.09.02 | J16: PPP storage is safe | K16: minor
A17: FO 04.06.01 | B17: Name applicators | C17: minor | I17: FV-SMART & GFS 32.09.03 | J17: PPS storage does not pose risk | K17: minor
A18: FO 07.06.02 | B18: Containers reused | C18: minor | I18: FV-SMART & GFS 32.09.05 | J18: Storage has light | K18: minor
A19: FO 07.06.03 | B19: Containers kept safely | C19: minor | I19: FV-SMART & GFS 32.10.01 | J19: Access to health checks | K19: minor
A20: FO 07.06.04 | B20: Containers disposed correctly | C20: minor | I20: FV-SMART & GFS 32.10.03 | J20: Accident procedure | K20: minor
A21: FO 07.04.02 | B21: PPS storage does not pose risk | C21: minor | I21: FV-SMART & GFS 32.10.04 | J21: Facilities deal with accidents | K21: minor
A22: FO 07.04.03 | B22: Storage has light | C22: minor | I22: FV-SMART & GFS 32.10.05 | J22: PPP transported safely | K22: minor
A23: FO 07.04.06 | B23: Accident procedure | C23: minor
A24: FO 07.04.07 | B24: Facilities deal with accidents | C24: minor
A25: FO 07.05.02 | B25: PPP transported safely | C25: minor
